{
 "c": {
  "kabardino": {
   "z": {},
   "l": [
    "43.9264",
    "44.1022"
   ]
  },
  "nalchik": {
   "z": {
    "360000": [
     "43.5017",
     "43.6147"
    ],
    "360003": [
     "43.4981",
     "43.6189"
    ],
    "360004": [
     "43.4981",
     "43.6189"
    ],
    "360005": [
     "43.5017",
     "43.6147"
    ],
    "360006": [
     "43.4981",
     "43.6189"
    ],
    "360012": [
     "43.4981",
     "43.6189"
    ],
    "360017": [
     "43.5017",
     "43.6147"
    ],
    "360019": [
     "43.5017",
     "43.6147"
    ],
    "360022": [
     "43.4981",
     "43.6189"
    ],
    "360024": [
     "43.5017",
     "43.6147"
    ],
    "360030": [
     "43.5017",
     "43.6147"
    ],
    "360032": [
     "43.5017",
     "43.6147"
    ],
    "360051": [
     "43.5017",
     "43.6147"
    ],
    "360903": [
     "43.4981",
     "43.6189"
    ],
    "361045": [
     "43.7556",
     "44.0381"
    ],
    "361202": [
     "43.4981",
     "43.6189"
    ]
   },
   "l": [
    "43.4981",
    "43.6189"
   ]
  },
  "arik": {
   "z": {},
   "l": [
    "43.5802",
    "44.1195"
   ]
  },
  "minskiy": {
   "z": {},
   "l": [
    "43.6894",
    "43.7697"
   ]
  },
  "soldatskaya": {
   "z": {},
   "l": [
    "43.8181",
    "43.8158"
   ]
  },
  "uchebnyy": {
   "z": {},
   "l": [
    "43.7850",
    "43.9192"
   ]
  },
  "dolinsk": {
   "z": {},
   "l": [
    "43.4672",
    "43.5739"
   ]
  },
  "baksan": {
   "z": {},
   "l": [
    "43.6881",
    "43.5369"
   ]
  },
  "yanikoy": {
   "z": {},
   "l": [
    "43.5447",
    "43.5131"
   ]
  },
  "shalushka": {
   "z": {
    "361424": [
     "43.5325",
     "43.5661"
    ]
   },
   "l": [
    "43.5325",
    "43.5661"
   ]
  },
  "dokshukino": {
   "z": {},
   "l": [
    "43.5575",
    "43.8508"
   ]
  },
  "chegem": {
   "z": {
    "361401": [
     "43.2833",
     "43.1333"
    ]
   },
   "l": [
    "43.2833",
    "43.1333"
   ]
  },
  "tyrnyauz": {
   "z": {},
   "l": [
    "43.3828",
    "42.9183"
   ]
  },
  "nartkala": {
   "z": {
    "361330": [
     "43.5575",
     "43.8508"
    ],
    "361331": [
     "43.5575",
     "43.8508"
    ]
   },
   "l": [
    "43.5575",
    "43.8508"
   ]
  },
  "nizhniy kurkuzhin": {
   "z": {},
   "l": [
    "43.7483",
    "43.3497"
   ]
  },
  "mayskiy": {
   "z": {},
   "l": [
    "43.6414",
    "44.0385"
   ]
  },
  "altud": {
   "z": {},
   "l": [
    "43.7219",
    "43.8658"
   ]
  },
  "terek": {
   "z": {},
   "l": [
    "43.4833",
    "44.1361"
   ]
  },
  "primalkinskoye": {
   "z": {},
   "l": [
    "43.7467",
    "44.0083"
   ]
  },
  "kuyan": {
   "z": {},
   "l": [
    "43.6222",
    "44.1271"
   ]
  },
  "prokhladnyy": {
   "z": {},
   "l": [
    "43.7574",
    "44.0297"
   ]
  },
  "proletarskoye": {
   "z": {},
   "l": [
    "43.8457",
    "44.0436"
   ]
  },
  "nartan": {
   "z": {},
   "l": [
    "43.5108",
    "43.6994"
   ]
  },
  "zalukokoazhe": {
   "z": {},
   "l": [
    "43.9039",
    "43.2156"
   ]
  },
  "psygansu": {
   "z": {},
   "l": [
    "43.4194",
    "43.7936"
   ]
  },
  "zayukovo": {
   "z": {},
   "l": [
    "43.6161",
    "43.3339"
   ]
  },
  "babugent": {
   "z": {},
   "l": [
    "43.2794",
    "43.5502"
   ]
  },
  "germenchik": {
   "z": {},
   "l": [
    "43.5939",
    "43.7661"
   ]
  },
  "sarmakovo": {
   "z": {},
   "l": [
    "43.7456",
    "43.2003"
   ]
  }
 },
 "l": [
  "43.4981",
  "43.6189"
 ]
}