{
 "c": {
  "kanagawa": {
   "z": {},
   "l": [
    "37.5833",
    "139.9167"
   ]
  },
  "fukushima": {
   "z": {},
   "l": [
    "37.7500",
    "140.4678"
   ]
  },
  "murata": {
   "z": {},
   "l": [
    "37.5667",
    "139.8500"
   ]
  },
  "iwaki": {
   "z": {},
   "l": [
    "37.0500",
    "140.8833"
   ]
  },
  "sukagawa": {
   "z": {},
   "l": [
    "37.2833",
    "140.3833"
   ]
  },
  "komiya": {
   "z": {},
   "l": [
    "37.6667",
    "140.7833"
   ]
  },
  "shirane": {
   "z": {},
   "l": [
    "37.8500",
    "140.6500"
   ]
  },
  "ajima": {
   "z": {},
   "l": [
    "37.2000",
    "139.7667"
   ]
  },
  "tokiwa": {
   "z": {},
   "l": [
    "37.4333",
    "140.6500"
   ]
  },
  "hamano": {
   "z": {},
   "l": [
    "37.1500",
    "139.4833"
   ]
  },
  "onahama": {
   "z": {},
   "l": [
    "36.9500",
    "140.9000"
   ]
  },
  "sugita": {
   "z": {},
   "l": [
    "37.5667",
    "140.4167"
   ]
  },
  "ohori": {
   "z": {},
   "l": [
    "37.4667",
    "140.9500"
   ]
  },
  "otaki": {
   "z": {},
   "l": [
    "37.8333",
    "140.3333"
   ]
  },
  "motomiya": {
   "z": {},
   "l": [
    "37.5167",
    "140.4000"
   ]
  },
  "koriyama": {
   "z": {},
   "l": [
    "37.4000",
    "140.3833"
   ]
  },
  "tsutsumi": {
   "z": {},
   "l": [
    "37.0667",
    "140.3667"
   ]
  },
  "hatori": {
   "z": {},
   "l": [
    "37.2667",
    "140.0833"
   ]
  },
  "iwao": {
   "z": {},
   "l": [
    "37.7000",
    "139.8500"
   ]
  },
  "hirota": {
   "z": {},
   "l": [
    "37.5500",
    "139.9333"
   ]
  },
  "miyama": {
   "z": {},
   "l": [
    "37.7333",
    "140.9167"
   ]
  },
  "ozawa": {
   "z": {},
   "l": [
    "37.5667",
    "141.0167"
   ]
  },
  "towada": {
   "z": {},
   "l": [
    "37.2333",
    "140.8500"
   ]
  },
  "naganuma": {
   "z": {},
   "l": [
    "37.2833",
    "140.2167"
   ]
  },
  "kotagawa": {
   "z": {},
   "l": [
    "37.1500",
    "140.2667"
   ]
  },
  "kumakura": {
   "z": {},
   "l": [
    "37.1500",
    "140.1667"
   ]
  },
  "nozawa": {
   "z": {},
   "l": [
    "37.5833",
    "139.6500"
   ]
  },
  "fukuhara": {
   "z": {},
   "l": [
    "37.4167",
    "140.3833"
   ]
  },
  "nakaji": {
   "z": {},
   "l": [
    "37.3833",
    "140.1333"
   ]
  },
  "kori": {
   "z": {},
   "l": [
    "37.8333",
    "140.5167"
   ]
  },
  "miyashita": {
   "z": {},
   "l": [
    "37.4667",
    "139.6333"
   ]
  },
  "tadano": {
   "z": {},
   "l": [
    "37.4000",
    "140.2667"
   ]
  },
  "kotaka": {
   "z": {},
   "l": [
    "37.2000",
    "140.4167"
   ]
  },
  "kitakata": {
   "z": {},
   "l": [
    "37.6500",
    "139.8667"
   ]
  },
  "matsukawa": {
   "z": {},
   "l": [
    "37.6500",
    "140.4667"
   ]
  },
  "mitsuwa": {
   "z": {},
   "l": [
    "37.5333",
    "140.0667"
   ]
  },
  "takatama": {
   "z": {},
   "l": [
    "37.4833",
    "140.2833"
   ]
  },
  "tamanoi": {
   "z": {},
   "l": [
    "37.5333",
    "140.3667"
   ]
  },
  "namie": {
   "z": {},
   "l": [
    "37.4833",
    "141.0000"
   ]
  },
  "toyoma": {
   "z": {},
   "l": [
    "36.9833",
    "140.9667"
   ]
  },
  "kanatsu": {
   "z": {},
   "l": [
    "37.3667",
    "139.3167"
   ]
  },
  "kito": {
   "z": {},
   "l": [
    "37.2667",
    "141.0000"
   ]
  },
  "kuma": {
   "z": {},
   "l": [
    "37.3833",
    "141.0167"
   ]
  },
  "itsumi": {
   "z": {},
   "l": [
    "37.7667",
    "140.4500"
   ]
  },
  "akimoto": {
   "z": {},
   "l": [
    "37.6500",
    "140.1167"
   ]
  },
  "miharu": {
   "z": {},
   "l": [
    "37.4333",
    "140.4833"
   ]
  },
  "inawashiro": {
   "z": {},
   "l": [
    "37.5667",
    "140.1167"
   ]
  },
  "onagawa": {
   "z": {},
   "l": [
    "37.6833",
    "140.1167"
   ]
  },
  "kanahashi": {
   "z": {},
   "l": [
    "37.5833",
    "139.9167"
   ]
  },
  "oshio": {
   "z": {},
   "l": [
    "37.6667",
    "139.9833"
   ]
  },
  "tadami": {
   "z": {},
   "l": [
    "37.3500",
    "139.3167"
   ]
  },
  "nihonmatsu": {
   "z": {},
   "l": [
    "37.5833",
    "140.4333"
   ]
  },
  "isobe": {
   "z": {},
   "l": [
    "37.7667",
    "140.9833"
   ]
  },
  "numajiri": {
   "z": {},
   "l": [
    "37.6333",
    "140.2667"
   ]
  },
  "sekita": {
   "z": {},
   "l": [
    "37.5000",
    "140.1500"
   ]
  },
  "uchikawa": {
   "z": {},
   "l": [
    "37.1500",
    "139.4833"
   ]
  },
  "joko": {
   "z": {},
   "l": [
    "37.4833",
    "140.1667"
   ]
  },
  "toyoda-machi": {
   "z": {},
   "l": [
    "37.4000",
    "140.4667"
   ]
  },
  "funehiki": {
   "z": {
    "9634312": [
     "37.4333",
     "140.5833"
    ]
   },
   "l": [
    "37.4333",
    "140.5833"
   ]
  },
  "nihommatsu": {
   "z": {},
   "l": [
    "37.5833",
    "140.4333"
   ]
  },
  "ena": {
   "z": {},
   "l": [
    "36.9667",
    "140.9667"
   ]
  },
  "miyazaki": {
   "z": {},
   "l": [
    "37.4833",
    "139.5333"
   ]
  },
  "kamikita": {
   "z": {},
   "l": [
    "37.7333",
    "140.5500"
   ]
  },
  "yanagawa": {
   "z": {},
   "l": [
    "37.8500",
    "140.6000"
   ]
  },
  "ono-niimachi": {
   "z": {},
   "l": [
    "37.2833",
    "140.6333"
   ]
  },
  "ishikawa": {
   "z": {},
   "l": [
    "37.1500",
    "140.4500"
   ]
  },
  "haranomachi": {
   "z": {},
   "l": [
    "37.6333",
    "140.9667"
   ]
  },
  "yabuki": {
   "z": {
    "9690251": [
     "37.2000",
     "140.3167"
    ]
   },
   "l": [
    "37.2000",
    "140.3167"
   ]
  },
  "tanagura": {
   "z": {},
   "l": [
    "37.0333",
    "140.3833"
   ]
  },
  "yamato": {
   "z": {},
   "l": [
    "37.6333",
    "139.7667"
   ]
  },
  "miyako": {
   "z": {},
   "l": [
    "37.5667",
    "139.8500"
   ]
  },
  "tajima": {
   "z": {},
   "l": [
    "37.1000",
    "140.2833"
   ]
  },
  "date": {
   "z": {
    "9600729": [
     "37.8167",
     "140.5000"
    ]
   },
   "l": [
    "37.8167",
    "140.5000"
   ]
  },
  "aizu": {
   "z": {},
   "l": [
    "37.5500",
    "139.9833"
   ]
  },
  "obama": {
   "z": {},
   "l": [
    "37.5500",
    "140.5000"
   ]
  },
  "atami": {
   "z": {},
   "l": [
    "37.4833",
    "140.2667"
   ]
  },
  "tanakura": {
   "z": {},
   "l": [
    "37.0333",
    "140.3833"
   ]
  },
  "ohira": {
   "z": {},
   "l": [
    "37.8500",
    "140.2833"
   ]
  },
  "yamaguchi": {
   "z": {},
   "l": [
    "37.2167",
    "139.5333"
   ]
  },
  "toyama": {
   "z": {},
   "l": [
    "36.9833",
    "140.9667"
   ]
  },
  "bange": {
   "z": {},
   "l": [
    "37.5667",
    "139.8167"
   ]
  },
  "jogo": {
   "z": {},
   "l": [
    "37.4833",
    "140.1667"
   ]
  },
  "kami-misaka": {
   "z": {},
   "l": [
    "37.1833",
    "140.6167"
   ]
  },
  "koori": {
   "z": {},
   "l": [
    "37.8333",
    "140.5167"
   ]
  },
  "niida": {
   "z": {},
   "l": [
    "37.3333",
    "140.3167"
   ]
  },
  "funatsu": {
   "z": {},
   "l": [
    "37.4000",
    "140.1333"
   ]
  },
  "tsukidate": {
   "z": {},
   "l": [
    "37.7333",
    "140.6167"
   ]
  },
  "shimo-tsushima": {
   "z": {},
   "l": [
    "37.5667",
    "140.7500"
   ]
  },
  "kammata": {
   "z": {},
   "l": [
    "37.3167",
    "140.6500"
   ]
  },
  "omogawa": {
   "z": {},
   "l": [
    "37.6833",
    "140.1167"
   ]
  },
  "kido": {
   "z": {},
   "l": [
    "37.2667",
    "141.0000"
   ]
  },
  "maeda": {
   "z": {},
   "l": [
    "37.0333",
    "140.7167"
   ]
  },
  "hanawa": {
   "z": {},
   "l": [
    "36.9500",
    "140.4167"
   ]
  },
  "naka-moniwa": {
   "z": {},
   "l": [
    "37.9167",
    "140.4333"
   ]
  },
  "shirasaka": {
   "z": {},
   "l": [
    "37.0833",
    "140.2000"
   ]
  },
  "adami": {
   "z": {},
   "l": [
    "37.4833",
    "140.2667"
   ]
  },
  "kaneyama": {
   "z": {},
   "l": [
    "37.0500",
    "140.3000"
   ]
  },
  "suginomecho": {
   "z": {},
   "l": [
    "37.7500",
    "140.4667"
   ]
  },
  "hukusima": {
   "z": {
    "9718172": [
     "37.7500",
     "140.4678"
    ]
   },
   "l": [
    "37.7500",
    "140.4678"
   ]
  },
  "fukushima-shi": {
   "z": {},
   "l": [
    "37.7500",
    "140.4678"
   ]
  },
  "watari": {
   "z": {},
   "l": [
    "37.7500",
    "140.4667"
   ]
  },
  "shirakawa": {
   "z": {},
   "l": [
    "37.1333",
    "140.2167"
   ]
  },
  "soma": {
   "z": {},
   "l": [
    "37.7928",
    "140.9294"
   ]
  },
  "aizu-wakamatsu": {
   "z": {},
   "l": [
    "37.4914",
    "139.9455"
   ]
  },
  "minami-soma": {
   "z": {},
   "l": [
    "37.6291",
    "140.9787"
   ]
  },
  "tamura": {
   "z": {},
   "l": [
    "37.4306",
    "140.6034"
   ]
  },
  "kawaguchi": {
   "z": {},
   "l": [
    "37.5000",
    "139.7000"
   ]
  },
  "omika": {
   "z": {},
   "l": [
    "37.6000",
    "141.0000"
   ]
  },
  "iizaka": {
   "z": {},
   "l": [
    "37.8333",
    "140.4500"
   ]
  },
  "kanda": {
   "z": {},
   "l": [
    "37.2000",
    "140.3833"
   ]
  },
  "asakawa": {
   "z": {},
   "l": [
    "37.0833",
    "140.4167"
   ]
  },
  "kashiwabara": {
   "z": {},
   "l": [
    "37.5167",
    "140.8167"
   ]
  },
  "ishimushiro": {
   "z": {},
   "l": [
    "37.5333",
    "140.2667"
   ]
  },
  "taira": {
   "z": {},
   "l": [
    "37.0500",
    "140.9167"
   ]
  },
  "takada": {
   "z": {},
   "l": [
    "37.4500",
    "139.8500"
   ]
  },
  "izumi": {
   "z": {},
   "l": [
    "36.9500",
    "140.8500"
   ]
  },
  "takayashiki": {
   "z": {},
   "l": [
    "37.7667",
    "140.5833"
   ]
  },
  "niijuku": {
   "z": {},
   "l": [
    "37.0333",
    "140.5000"
   ]
  },
  "ogura": {
   "z": {},
   "l": [
    "37.4667",
    "140.2833"
   ]
  },
  "shinyashiki": {
   "z": {},
   "l": [
    "37.5333",
    "140.1333"
   ]
  },
  "nagaoka": {
   "z": {},
   "l": [
    "37.8167",
    "140.5000"
   ]
  },
  "onogawa": {
   "z": {},
   "l": [
    "37.6833",
    "140.1167"
   ]
  },
  "shinjuku": {
   "z": {},
   "l": [
    "37.0333",
    "140.5000"
   ]
  }
 },
 "l": [
  "37.4000",
  "140.3833"
 ]
}