{
 "c": {
  "matsue": {
   "z": {},
   "l": [
    "35.4722",
    "133.0506"
   ]
  },
  "otsuka": {
   "z": {},
   "l": [
    "35.3833",
    "133.2667"
   ]
  },
  "masuda": {
   "z": {},
   "l": [
    "34.6667",
    "131.8500"
   ]
  },
  "hirata": {
   "z": {},
   "l": [
    "35.2167",
    "132.9333"
   ]
  },
  "izumo": {
   "z": {},
   "l": [
    "35.3667",
    "132.7667"
   ]
  },
  "asai": {
   "z": {},
   "l": [
    "34.9000",
    "132.1000"
   ]
  },
  "kamaya": {
   "z": {},
   "l": [
    "36.1833",
    "133.2333"
   ]
  },
  "hamada": {
   "z": {},
   "l": [
    "34.8833",
    "132.0833"
   ]
  },
  "arashima": {
   "z": {},
   "l": [
    "35.4333",
    "133.1833"
   ]
  },
  "taki": {
   "z": {},
   "l": [
    "35.2667",
    "132.6167"
   ]
  },
  "shinji": {
   "z": {},
   "l": [
    "35.4000",
    "132.9000"
   ]
  },
  "takatsu": {
   "z": {},
   "l": [
    "34.6833",
    "131.7833"
   ]
  },
  "nichihara": {
   "z": {},
   "l": [
    "34.5333",
    "131.8333"
   ]
  },
  "ichiyama": {
   "z": {},
   "l": [
    "34.9333",
    "132.3167"
   ]
  },
  "torii": {
   "z": {},
   "l": [
    "35.2167",
    "132.4833"
   ]
  },
  "kizuki": {
   "z": {},
   "l": [
    "35.4000",
    "132.6667"
   ]
  },
  "sanada": {
   "z": {},
   "l": [
    "34.4000",
    "131.9000"
   ]
  },
  "hashi": {
   "z": {},
   "l": [
    "34.9667",
    "132.1500"
   ]
  },
  "miho": {
   "z": {},
   "l": [
    "35.5667",
    "133.3167"
   ]
  },
  "koryo": {
   "z": {},
   "l": [
    "35.3000",
    "132.6667"
   ]
  },
  "imada": {
   "z": {},
   "l": [
    "34.8500",
    "132.1667"
   ]
  },
  "tamaru": {
   "z": {},
   "l": [
    "34.4000",
    "131.9000"
   ]
  },
  "hishi": {
   "z": {},
   "l": [
    "36.1000",
    "133.0833"
   ]
  },
  "koura": {
   "z": {},
   "l": [
    "35.5167",
    "132.9667"
   ]
  },
  "shimojo": {
   "z": {},
   "l": [
    "35.1000",
    "132.5333"
   ]
  },
  "taishi": {
   "z": {},
   "l": [
    "35.4000",
    "132.6667"
   ]
  },
  "wake": {
   "z": {},
   "l": [
    "35.0000",
    "132.2000"
   ]
  },
  "ichimura": {
   "z": {},
   "l": [
    "35.0000",
    "132.2833"
   ]
  },
  "yamasa": {
   "z": {},
   "l": [
    "35.3167",
    "133.1167"
   ]
  },
  "tako": {
   "z": {},
   "l": [
    "35.6000",
    "133.1000"
   ]
  },
  "oike": {
   "z": {},
   "l": [
    "35.3167",
    "132.6500"
   ]
  },
  "kitagata": {
   "z": {},
   "l": [
    "36.2833",
    "133.2333"
   ]
  },
  "kambara": {
   "z": {},
   "l": [
    "34.5667",
    "132.0167"
   ]
  },
  "ushio": {
   "z": {},
   "l": [
    "35.0167",
    "132.6333"
   ]
  },
  "nima": {
   "z": {},
   "l": [
    "35.1500",
    "132.4000"
   ]
  },
  "akatsuka": {
   "z": {},
   "l": [
    "35.0500",
    "132.6000"
   ]
  },
  "aika": {
   "z": {},
   "l": [
    "35.4667",
    "132.9500"
   ]
  },
  "taisha": {
   "z": {},
   "l": [
    "35.4000",
    "132.6667"
   ]
  },
  "yasugi": {
   "z": {},
   "l": [
    "35.4333",
    "133.2500"
   ]
  },
  "gotsu": {
   "z": {},
   "l": [
    "35.0000",
    "132.2167"
   ]
  },
  "kuromatsu": {
   "z": {},
   "l": [
    "35.0667",
    "132.3167"
   ]
  },
  "naoe": {
   "z": {},
   "l": [
    "35.3833",
    "132.8167"
   ]
  },
  "hane": {
   "z": {},
   "l": [
    "35.2333",
    "132.5333"
   ]
  },
  "saki": {
   "z": {},
   "l": [
    "35.0000",
    "132.4167"
   ]
  },
  "muraki": {
   "z": {},
   "l": [
    "34.4833",
    "131.7167"
   ]
  },
  "sumikawa": {
   "z": {},
   "l": [
    "34.7500",
    "131.9833"
   ]
  },
  "oda": {
   "z": {},
   "l": [
    "35.1833",
    "132.5000"
   ]
  },
  "imaichi": {
   "z": {},
   "l": [
    "34.8500",
    "132.2667"
   ]
  },
  "furumi": {
   "z": {},
   "l": [
    "36.0167",
    "133.0333"
   ]
  },
  "matsushiro": {
   "z": {},
   "l": [
    "35.1667",
    "132.4833"
   ]
  },
  "koshi": {
   "z": {},
   "l": [
    "35.3500",
    "132.7333"
   ]
  },
  "minami": {
   "z": {},
   "l": [
    "36.0667",
    "133.1000"
   ]
  },
  "mitoya": {
   "z": {},
   "l": [
    "35.2833",
    "132.8667"
   ]
  },
  "hirakawa": {
   "z": {},
   "l": [
    "36.2833",
    "130.8500"
   ]
  },
  "kawamoto": {
   "z": {},
   "l": [
    "34.9833",
    "132.5000"
   ]
  },
  "fukuyama": {
   "z": {},
   "l": [
    "34.4167",
    "131.8333"
   ]
  },
  "daito": {
   "z": {},
   "l": [
    "35.3167",
    "132.9667"
   ]
  },
  "mizu": {
   "z": {},
   "l": [
    "35.5167",
    "133.0333"
   ]
  },
  "honjo": {
   "z": {},
   "l": [
    "35.5000",
    "133.1333"
   ]
  },
  "kitsuki": {
   "z": {},
   "l": [
    "35.4000",
    "132.6667"
   ]
  },
  "shobara": {
   "z": {},
   "l": [
    "35.3833",
    "132.8667"
   ]
  },
  "uyagawa": {
   "z": {},
   "l": [
    "34.9667",
    "132.1667"
   ]
  },
  "toyota": {
   "z": {},
   "l": [
    "36.1000",
    "133.1333"
   ]
  },
  "hurumi": {
   "z": {},
   "l": [
    "36.0167",
    "133.0333"
   ]
  },
  "sano": {
   "z": {},
   "l": [
    "34.8833",
    "132.1667"
   ]
  },
  "hama": {
   "z": {},
   "l": [
    "35.5667",
    "133.0500"
   ]
  },
  "kamishima": {
   "z": {},
   "l": [
    "35.3333",
    "132.8500"
   ]
  },
  "yamaguchi": {
   "z": {},
   "l": [
    "35.1667",
    "132.6333"
   ]
  },
  "iya": {
   "z": {},
   "l": [
    "35.4333",
    "133.1500"
   ]
  },
  "yunotsu": {
   "z": {},
   "l": [
    "35.0833",
    "132.3500"
   ]
  },
  "daiku": {
   "z": {},
   "l": [
    "36.2500",
    "133.3667"
   ]
  },
  "matsue-shi": {
   "z": {},
   "l": [
    "35.4722",
    "133.0506"
   ]
  },
  "higashi-asahicho": {
   "z": {
    "6991211": [
     "35.4667",
     "133.0667"
    ]
   },
   "l": [
    "35.4667",
    "133.0667"
   ]
  },
  "matue": {
   "z": {},
   "l": [
    "35.4722",
    "133.0506"
   ]
  },
  "kamo": {
   "z": {},
   "l": [
    "35.3333",
    "132.9167"
   ]
  },
  "ikeda": {
   "z": {},
   "l": [
    "35.1333",
    "132.5833"
   ]
  },
  "kisuki": {
   "z": {},
   "l": [
    "35.2833",
    "132.9000"
   ]
  },
  "yokota": {
   "z": {},
   "l": [
    "34.6167",
    "131.8000"
   ]
  },
  "oyamacho": {
   "z": {},
   "l": [
    "35.3667",
    "132.7333"
   ]
  },
  "misumi": {
   "z": {},
   "l": [
    "34.7667",
    "131.9667"
   ]
  },
  "katae": {
   "z": {},
   "l": [
    "35.5667",
    "133.1833"
   ]
  },
  "oyama": {
   "z": {},
   "l": [
    "35.3667",
    "132.7333"
   ]
  },
  "watari": {
   "z": {},
   "l": [
    "35.5167",
    "133.2000"
   ]
  },
  "ama": {
   "z": {},
   "l": [
    "36.1000",
    "133.1167"
   ]
  },
  "ooi": {
   "z": {},
   "l": [
    "36.0500",
    "133.1000"
   ]
  },
  "koizu": {
   "z": {},
   "l": [
    "35.5000",
    "132.8333"
   ]
  },
  "minari": {
   "z": {},
   "l": [
    "35.2000",
    "133.0000"
   ]
  }
 },
 "l": [
  "35.3667",
  "132.7667"
 ]
}