{
 "c": {
  "iquique": {
   "z": {},
   "l": [
    "-20.2208",
    "-70.1431"
   ]
  },
  "la calera": {
   "z": {},
   "l": [
    "-20.3667",
    "-69.3833"
   ]
  },
  "alto hospicio": {
   "z": {},
   "l": [
    "-20.2500",
    "-70.1167"
   ]
  },
  "pozo almonte": {
   "z": {},
   "l": [
    "-20.2667",
    "-69.8000"
   ]
  },
  "tarapaca": {
   "z": {},
   "l": [
    "-19.9167",
    "-69.5167"
   ]
  },
  "pica": {
   "z": {},
   "l": [
    "-20.5000",
    "-69.3500"
   ]
  },
  "argentina": {
   "z": {},
   "l": [
    "-20.4500",
    "-69.8833"
   ]
  },
  "huara": {
   "z": {},
   "l": [
    "-19.9833",
    "-69.7833"
   ]
  }
 },
 "l": []
}