{
 "c": {
  "zwijndrecht": {
   "z": {
    "2070": [
     "51.2000",
     "4.3500"
    ]
   },
   "l": [
    "51.2167",
    "4.3333"
   ]
  },
  "edegem": {
   "z": {
    "2650": [
     "51.1500",
     "4.4500"
    ]
   },
   "l": [
    "51.1500",
    "4.4500"
   ]
  },
  "essen": {
   "z": {
    "2910": [
     "51.4667",
     "4.4667"
    ]
   },
   "l": [
    "51.4667",
    "4.4667"
   ]
  },
  "herentals": {
   "z": {
    "2200": [
     "51.1833",
     "4.8333"
    ]
   },
   "l": [
    "51.1833",
    "4.8333"
   ]
  },
  "puurs": {
   "z": {
    "2870": [
     "51.0833",
     "4.2833"
    ]
   },
   "l": [
    "51.0833",
    "4.2833"
   ]
  },
  "antwerpen": {
   "z": {
    "2000": [
     "51.2167",
     "4.4167"
    ],
    "2018": [
     "51.2167",
     "4.4167"
    ],
    "2020": [
     "51.2167",
     "4.4167"
    ],
    "2030": [
     "51.2167",
     "4.4167"
    ],
    "2040": [
     "51.2167",
     "4.4167"
    ],
    "2050": [
     "51.2167",
     "4.4167"
    ],
    "2060": [
     "51.2167",
     "4.4167"
    ],
    "2080": [
     "51.2167",
     "4.4167"
    ]
   },
   "l": [
    "51.2167",
    "4.4167"
   ]
  },
  "antwerp": {
   "z": {
    "9056": [
     "51.2167",
     "4.4167"
    ]
   },
   "l": [
    "51.2167",
    "4.4167"
   ]
  },
  "boom": {
   "z": {
    "2850": [
     "51.0833",
     "4.3667"
    ]
   },
   "l": [
    "51.0833",
    "4.3667"
   ]
  },
  "hoboken": {
   "z": {
    "2660": [
     "51.2167",
     "4.4167"
    ]
   },
   "l": [
    "51.1667",
    "4.3500"
   ]
  },
  "berg": {
   "z": {},
   "l": [
    "51.2833",
    "5.0667"
   ]
  },
  "schoten": {
   "z": {
    "2900": [
     "51.2500",
     "4.5000"
    ]
   },
   "l": [
    "51.2500",
    "4.5000"
   ]
  },
  "kontich": {
   "z": {
    "2550": [
     "51.1000",
     "4.4500"
    ]
   },
   "l": [
    "51.1333",
    "4.4500"
   ]
  },
  "turnhout": {
   "z": {
    "2300": [
     "51.3167",
     "4.9500"
    ]
   },
   "l": [
    "51.3167",
    "4.9500"
   ]
  },
  "bornem": {
   "z": {
    "2880": [
     "51.1000",
     "4.2333"
    ]
   },
   "l": [
    "51.1000",
    "4.2333"
   ]
  },
  "mechelen": {
   "z": {
    "2800": [
     "51.0333",
     "4.4667"
    ]
   },
   "l": [
    "51.0333",
    "4.4667"
   ]
  },
  "geel": {
   "z": {
    "2440": [
     "51.1667",
     "5.0000"
    ]
   },
   "l": [
    "51.1667",
    "5.0000"
   ]
  },
  "wilrijk": {
   "z": {
    "2610": [
     "51.2167",
     "4.4167"
    ]
   },
   "l": [
    "51.1667",
    "4.4000"
   ]
  },
  "sint-katelijne-waver": {
   "z": {
    "2860": [
     "51.0667",
     "4.5333"
    ]
   },
   "l": [
    "51.0667",
    "4.5333"
   ]
  },
  "willebroek": {
   "z": {
    "2830": [
     "51.0667",
     "4.4000"
    ]
   },
   "l": [
    "51.0667",
    "4.3667"
   ]
  },
  "deurne": {
   "z": {
    "2100": [
     "51.2167",
     "4.4167"
    ]
   },
   "l": [
    "51.2167",
    "4.4667"
   ]
  },
  "duffel": {
   "z": {
    "2570": [
     "51.1000",
     "4.5167"
    ]
   },
   "l": [
    "51.1000",
    "4.5167"
   ]
  },
  "aartselaar": {
   "z": {
    "2630": [
     "51.1333",
     "4.3833"
    ]
   },
   "l": [
    "51.1333",
    "4.3833"
   ]
  },
  "westmalle": {
   "z": {
    "2168": [
     "51.3000",
     "4.6833"
    ]
   },
   "l": [
    "51.3000",
    "4.6833"
   ]
  },
  "wommelgem": {
   "z": {
    "2160": [
     "51.2000",
     "4.5167"
    ]
   },
   "l": [
    "51.2000",
    "4.5167"
   ]
  },
  "reet": {
   "z": {},
   "l": [
    "51.1000",
    "4.4167"
   ]
  },
  "mortsel": {
   "z": {
    "2640": [
     "51.1667",
     "4.4667"
    ]
   },
   "l": [
    "51.1667",
    "4.4667"
   ]
  },
  "balen": {
   "z": {
    "2490": [
     "51.1667",
     "5.1500"
    ],
    "2491": [
     "51.1500",
     "5.1667"
    ]
   },
   "l": [
    "51.1667",
    "5.1500"
   ]
  },
  "rumst": {
   "z": {
    "2840": [
     "51.0833",
     "4.4000"
    ]
   },
   "l": [
    "51.0833",
    "4.4167"
   ]
  },
  "schelle": {
   "z": {
    "2627": [
     "51.1333",
     "4.3333"
    ]
   },
   "l": [
    "51.1333",
    "4.3333"
   ]
  },
  "ekeren": {
   "z": {
    "2180": [
     "51.2167",
     "4.4167"
    ]
   },
   "l": [
    "51.2833",
    "4.4167"
   ]
  },
  "westerlo": {
   "z": {
    "2260": [
     "51.0833",
     "4.9167"
    ]
   },
   "l": [
    "51.0833",
    "4.9167"
   ]
  },
  "goor": {
   "z": {},
   "l": [
    "51.0500",
    "4.7167"
   ]
  },
  "olen": {
   "z": {
    "2250": [
     "51.1500",
     "4.8500"
    ]
   },
   "l": [
    "51.1500",
    "4.8500"
   ]
  },
  "weert": {
   "z": {},
   "l": [
    "51.1000",
    "4.2000"
   ]
  },
  "haag": {
   "z": {},
   "l": [
    "51.1833",
    "5.0667"
   ]
  },
  "arendonk": {
   "z": {
    "2370": [
     "51.3167",
     "5.0833"
    ],
    "2730": [
     "51.3167",
     "5.0833"
    ]
   },
   "l": [
    "51.3167",
    "5.0833"
   ]
  },
  "lichtaart": {
   "z": {},
   "l": [
    "51.2333",
    "4.9000"
   ]
  },
  "ruisbroek": {
   "z": {},
   "l": [
    "51.0833",
    "4.3333"
   ]
  },
  "hoogstraten": {
   "z": {
    "2320": [
     "51.4000",
     "4.7667"
    ]
   },
   "l": [
    "51.4000",
    "4.7667"
   ]
  },
  "grobbendonk": {
   "z": {
    "2280": [
     "51.2000",
     "4.7167"
    ]
   },
   "l": [
    "51.2000",
    "4.7167"
   ]
  },
  "brasschaat": {
   "z": {
    "2130": [
     "51.2833",
     "4.4500"
    ],
    "2930": [
     "51.2833",
     "4.4500"
    ]
   },
   "l": [
    "51.2833",
    "4.4500"
   ]
  },
  "zandhoven": {
   "z": {
    "2240": [
     "51.1833",
     "4.6333"
    ]
   },
   "l": [
    "51.2167",
    "4.6500"
   ]
  },
  "grand": {
   "z": {},
   "l": [
    "51.2000",
    "4.4667"
   ]
  },
  "beerse": {
   "z": {
    "2340": [
     "51.3000",
     "4.7833"
    ]
   },
   "l": [
    "51.3167",
    "4.8667"
   ]
  },
  "leest": {
   "z": {},
   "l": [
    "51.0333",
    "4.4167"
   ]
  },
  "booischot": {
   "z": {
    "2221": [
     "51.1605",
     "4.7784"
    ]
   },
   "l": [
    "51.0500",
    "4.7667"
   ]
  },
  "borgerhout": {
   "z": {
    "2140": [
     "51.2167",
     "4.4167"
    ]
   },
   "l": [
    "51.1167",
    "5.0833"
   ]
  },
  "kalmthout": {
   "z": {
    "2920": [
     "51.3833",
     "4.4667"
    ]
   },
   "l": [
    "51.3833",
    "4.4667"
   ]
  },
  "dessel": {
   "z": {
    "2480": [
     "51.2333",
     "5.1167"
    ]
   },
   "l": [
    "51.2333",
    "5.1167"
   ]
  },
  "schriek": {
   "z": {
    "2223": [
     "51.1605",
     "4.7784"
    ]
   },
   "l": [
    "51.0333",
    "4.6833"
   ]
  },
  "waarloos": {
   "z": {},
   "l": [
    "51.1000",
    "4.4500"
   ]
  },
  "boechout": {
   "z": {
    "2530": [
     "51.1667",
     "4.5000"
    ]
   },
   "l": [
    "51.1667",
    "4.5000"
   ]
  },
  "lint": {
   "z": {
    "2547": [
     "51.1333",
     "4.5000"
    ]
   },
   "l": [
    "51.1333",
    "4.5000"
   ]
  },
  "sint-amands": {
   "z": {
    "2890": [
     "51.0500",
     "4.2000"
    ]
   },
   "l": [
    "51.0500",
    "4.2000"
   ]
  },
  "merksem": {
   "z": {
    "2170": [
     "51.2167",
     "4.4167"
    ]
   },
   "l": [
    "51.2500",
    "4.4500"
   ]
  },
  "kapellen": {
   "z": {
    "2950": [
     "51.3167",
     "4.4333"
    ]
   },
   "l": [
    "51.3167",
    "4.4333"
   ]
  },
  "weelde": {
   "z": {
    "2381": [
     "51.3667",
     "5.0000"
    ]
   },
   "l": [
    "51.4167",
    "5.0000"
   ]
  },
  "tisselt": {
   "z": {},
   "l": [
    "51.0333",
    "4.3667"
   ]
  },
  "oevel": {
   "z": {},
   "l": [
    "51.1333",
    "4.8833"
   ]
  },
  "meer": {
   "z": {
    "2321": [
     "51.4500",
     "4.7333"
    ]
   },
   "l": [
    "51.1000",
    "5.0000"
   ]
  },
  "westmeerbeek": {
   "z": {},
   "l": [
    "51.0667",
    "4.8500"
   ]
  },
  "winkel": {
   "z": {},
   "l": [
    "51.2667",
    "4.9500"
   ]
  },
  "itterbeek": {
   "z": {},
   "l": [
    "51.1167",
    "4.5500"
   ]
  },
  "merksplas": {
   "z": {
    "2330": [
     "51.3667",
     "4.8667"
    ]
   },
   "l": [
    "51.3667",
    "4.8667"
   ]
  },
  "lips": {
   "z": {},
   "l": [
    "51.1500",
    "4.5667"
   ]
  },
  "breendonk": {
   "z": {},
   "l": [
    "51.0500",
    "4.3333"
   ]
  },
  "putte": {
   "z": {
    "2580": [
     "51.0667",
     "4.6333"
    ]
   },
   "l": [
    "51.0667",
    "4.6333"
   ]
  },
  "veerle": {
   "z": {
    "2431": [
     "51.0500",
     "4.8833"
    ]
   },
   "l": [
    "51.0667",
    "5.0000"
   ]
  },
  "hulshout": {
   "z": {
    "2235": [
     "51.0500",
     "4.8000"
    ]
   },
   "l": [
    "51.0833",
    "4.7833"
   ]
  },
  "meerle": {
   "z": {
    "2328": [
     "51.4000",
     "4.7667"
    ]
   },
   "l": [
    "51.4667",
    "4.8000"
   ]
  },
  "oelegem": {
   "z": {},
   "l": [
    "51.2167",
    "4.5833"
   ]
  },
  "ravels": {
   "z": {
    "2380": [
     "51.3667",
     "5.0000"
    ]
   },
   "l": [
    "51.3667",
    "5.0000"
   ]
  },
  "heist-op-den-berg": {
   "z": {
    "2220": [
     "51.1605",
     "4.7784"
    ]
   },
   "l": [
    "51.0833",
    "4.7167"
   ]
  },
  "emblem": {
   "z": {},
   "l": [
    "51.1667",
    "4.6000"
   ]
  },
  "biest": {
   "z": {},
   "l": [
    "51.1667",
    "4.3833"
   ]
  },
  "tielen": {
   "z": {},
   "l": [
    "51.2333",
    "4.8833"
   ]
  },
  "rijmenam": {
   "z": {},
   "l": [
    "51.0000",
    "4.5667"
   ]
  },
  "den berg": {
   "z": {},
   "l": [
    "51.1667",
    "4.3333"
   ]
  },
  "nijlen": {
   "z": {
    "2560": [
     "51.1667",
     "4.6500"
    ]
   },
   "l": [
    "51.1667",
    "4.6500"
   ]
  },
  "schilde": {
   "z": {
    "2790": [
     "51.2333",
     "4.5667"
    ],
    "2970": [
     "51.2333",
     "4.5667"
    ]
   },
   "l": [
    "51.2333",
    "4.5667"
   ]
  },
  "vosselaar": {
   "z": {
    "2350": [
     "51.3167",
     "4.8833"
    ]
   },
   "l": [
    "51.3167",
    "4.8833"
   ]
  },
  "eindhoven": {
   "z": {},
   "l": [
    "51.3333",
    "4.6333"
   ]
  },
  "wijnegem": {
   "z": {
    "2110": [
     "51.2333",
     "4.5333"
    ]
   },
   "l": [
    "51.2333",
    "4.5333"
   ]
  },
  "overheid": {
   "z": {},
   "l": [
    "51.0667",
    "4.2667"
   ]
  },
  "laer": {
   "z": {},
   "l": [
    "51.0667",
    "4.7500"
   ]
  },
  "eigen": {
   "z": {},
   "l": [
    "51.3167",
    "5.0000"
   ]
  },
  "dept": {
   "z": {},
   "l": [
    "51.1333",
    "4.8000"
   ]
  },
  "bell": {
   "z": {},
   "l": [
    "51.1667",
    "5.0667"
   ]
  },
  "bosch": {
   "z": {},
   "l": [
    "51.0667",
    "4.7167"
   ]
  },
  "steenweg": {
   "z": {},
   "l": [
    "51.2333",
    "4.5833"
   ]
  },
  "rijkevorsel": {
   "z": {
    "2310": [
     "51.3500",
     "4.7667"
    ]
   },
   "l": [
    "51.3500",
    "4.7667"
   ]
  },
  "lille": {
   "z": {
    "2275": [
     "51.2667",
     "4.7667"
    ]
   },
   "l": [
    "51.2333",
    "4.8333"
   ]
  },
  "grobbendonck": {
   "z": {},
   "l": [
    "51.2000",
    "4.7167"
   ]
  },
  "meerhout": {
   "z": {
    "2450": [
     "51.3500",
     "4.7500"
    ]
   },
   "l": [
    "51.1333",
    "5.0833"
   ]
  },
  "westerloo": {
   "z": {},
   "l": [
    "51.0833",
    "4.9167"
   ]
  },
  "brecht": {
   "z": {
    "2960": [
     "51.3500",
     "4.6833"
    ]
   },
   "l": [
    "51.3500",
    "4.6333"
   ]
  },
  "hulst": {
   "z": {},
   "l": [
    "51.1167",
    "4.5333"
   ]
  },
  "eikevliet": {
   "z": {},
   "l": [
    "51.1000",
    "4.3000"
   ]
  },
  "borgeind": {
   "z": {},
   "l": [
    "51.2500",
    "4.4833"
   ]
  },
  "rustoord": {
   "z": {},
   "l": [
    "51.3000",
    "4.4667"
   ]
  },
  "vorselaar": {
   "z": {
    "2290": [
     "51.2000",
     "4.7667"
    ]
   },
   "l": [
    "51.2000",
    "4.7667"
   ]
  },
  "beurs": {
   "z": {},
   "l": [
    "51.1167",
    "4.4167"
   ]
  },
  "reeth": {
   "z": {},
   "l": [
    "51.1000",
    "4.4167"
   ]
  },
  "wezel": {
   "z": {},
   "l": [
    "51.0500",
    "4.9167"
   ]
  },
  "wilmarsdonk": {
   "z": {},
   "l": [
    "51.2833",
    "4.3667"
   ]
  },
  "bonheiden": {
   "z": {
    "2820": [
     "51.0226",
     "4.5471"
    ]
   },
   "l": [
    "51.0333",
    "4.5333"
   ]
  },
  "hombeek": {
   "z": {
    "2811": [
     "51.0333",
     "4.4667"
    ]
   },
   "l": [
    "51.0167",
    "4.4500"
   ]
  },
  "hemiksem": {
   "z": {
    "2620": [
     "51.1500",
     "4.3500"
    ]
   },
   "l": [
    "51.1500",
    "4.3500"
   ]
  },
  "itegem": {
   "z": {
    "2222": [
     "51.1605",
     "4.7784"
    ]
   },
   "l": [
    "51.1000",
    "4.7333"
   ]
  },
  "dorp": {
   "z": {},
   "l": [
    "51.4000",
    "4.4667"
   ]
  },
  "veldhoven": {
   "z": {},
   "l": [
    "51.1667",
    "4.8167"
   ]
  },
  "kruis": {
   "z": {},
   "l": [
    "51.2000",
    "4.5333"
   ]
  },
  "nieuwland": {
   "z": {},
   "l": [
    "51.2000",
    "4.3167"
   ]
  },
  "herenthout": {
   "z": {
    "2270": [
     "51.1500",
     "4.7667"
    ]
   },
   "l": [
    "51.1500",
    "4.7667"
   ]
  },
  "oostmalle": {
   "z": {},
   "l": [
    "51.3000",
    "4.7333"
   ]
  },
  "kasterlee": {
   "z": {
    "2460": [
     "51.2333",
     "4.8833"
    ]
   },
   "l": [
    "51.2500",
    "4.9500"
   ]
  },
  "walcourt": {
   "z": {
    "5650": [
     "50.2500",
     "4.4167"
    ]
   },
   "l": [
    "50.2500",
    "4.4167"
   ]
  },
  "broechem": {
   "z": {},
   "l": [
    "51.1833",
    "4.6000"
   ]
  },
  "zandstraat": {
   "z": {},
   "l": [
    "51.1500",
    "4.7167"
   ]
  },
  "retie": {
   "z": {
    "2470": [
     "51.2667",
     "5.0667"
    ]
   },
   "l": [
    "51.2667",
    "5.0667"
   ]
  },
  "hove": {
   "z": {
    "2540": [
     "51.1500",
     "4.4667"
    ]
   },
   "l": [
    "51.1500",
    "4.4667"
   ]
  },
  "zoersel": {
   "z": {
    "2980": [
     "51.2667",
     "4.7000"
    ]
   },
   "l": [
    "51.2667",
    "4.7000"
   ]
  },
  "sluys": {
   "z": {},
   "l": [
    "51.2167",
    "5.1333"
   ]
  },
  "wuustwezel": {
   "z": {
    "2990": [
     "51.3833",
     "4.6000"
    ]
   },
   "l": [
    "51.3833",
    "4.6000"
   ]
  },
  "berlaar": {
   "z": {
    "2590": [
     "51.1333",
     "4.6500"
    ]
   },
   "l": [
    "51.1167",
    "4.6500"
   ]
  },
  "oud-turnhout": {
   "z": {
    "2360": [
     "51.3167",
     "4.9833"
    ]
   },
   "l": [
    "51.3167",
    "4.9833"
   ]
  },
  "stabroek": {
   "z": {
    "2940": [
     "51.3000",
     "4.3833"
    ]
   },
   "l": [
    "51.3333",
    "4.3667"
   ]
  },
  "herselt": {
   "z": {
    "2230": [
     "51.0333",
     "4.8167"
    ]
   },
   "l": [
    "51.0500",
    "4.8833"
   ]
  },
  "mol": {
   "z": {
    "2400": [
     "51.1833",
     "5.1000"
    ]
   },
   "l": [
    "51.1833",
    "5.1000"
   ]
  },
  "borsbeek": {
   "z": {
    "2150": [
     "51.2000",
     "4.4833"
    ]
   },
   "l": [
    "51.2000",
    "4.4833"
   ]
  },
  "ranst": {
   "z": {
    "2520": [
     "51.2000",
     "4.5500"
    ]
   },
   "l": [
    "51.2000",
    "4.5500"
   ]
  },
  "koningshooikt": {
   "z": {},
   "l": [
    "51.1000",
    "4.6000"
   ]
  },
  "niel": {
   "z": {
    "2845": [
     "51.1167",
     "4.3333"
    ]
   },
   "l": [
    "51.1167",
    "4.3333"
   ]
  },
  "oppuurs": {
   "z": {},
   "l": [
    "51.0667",
    "4.2500"
   ]
  },
  "heffen": {
   "z": {
    "2801": [
     "51.0333",
     "4.4667"
    ]
   },
   "l": [
    "51.0500",
    "4.4167"
   ]
  },
  "wiekevorst": {
   "z": {},
   "l": [
    "51.1167",
    "4.7833"
   ]
  },
  "baarle-hertog": {
   "z": {
    "2387": [
     "51.4500",
     "4.9333"
    ]
   },
   "l": [
    "51.4500",
    "4.9333"
   ]
  },
  "wortel": {
   "z": {
    "2323": [
     "51.4000",
     "4.7667"
    ]
   },
   "l": [
    "51.4000",
    "4.8000"
   ]
  },
  "den veind": {
   "z": {},
   "l": [
    "51.1167",
    "4.9667"
   ]
  },
  "morkhoven": {
   "z": {},
   "l": [
    "51.1167",
    "4.8000"
   ]
  },
  "berendrecht": {
   "z": {},
   "l": [
    "51.3333",
    "4.3167"
   ]
  },
  "heezemeir heide": {
   "z": {},
   "l": [
    "51.1167",
    "5.0167"
   ]
  },
  "onze-lieve-vrouw-waver": {
   "z": {
    "2861": [
     "51.0667",
     "4.5667"
    ]
   },
   "l": [
    "51.0667",
    "4.5667"
   ]
  },
  "peulis": {
   "z": {},
   "l": [
    "51.0333",
    "4.5833"
   ]
  },
  "poppel": {
   "z": {
    "2382": [
     "51.4500",
     "5.0333"
    ]
   },
   "l": [
    "51.4500",
    "5.0333"
   ]
  },
  "hoevenen": {
   "z": {},
   "l": [
    "51.3000",
    "4.3833"
   ]
  },
  "houthem": {
   "z": {},
   "l": [
    "51.2333",
    "4.9833"
   ]
  },
  "parwijs": {
   "z": {},
   "l": [
    "51.1000",
    "4.4833"
   ]
  },
  "kessel": {
   "z": {},
   "l": [
    "51.1333",
    "4.6167"
   ]
  },
  "liezele": {
   "z": {},
   "l": [
    "51.0667",
    "4.2833"
   ]
  },
  "olmen": {
   "z": {},
   "l": [
    "51.1500",
    "5.1667"
   ]
  },
  "meersel": {
   "z": {},
   "l": [
    "51.4833",
    "4.7667"
   ]
  },
  "minderhout": {
   "z": {
    "2322": [
     "51.4000",
     "4.7667"
    ]
   },
   "l": [
    "51.4167",
    "4.7667"
   ]
  },
  "bouwel": {
   "z": {
    "2288": [
     "51.1667",
     "4.7333"
    ]
   },
   "l": [
    "51.1667",
    "4.7333"
   ]
  },
  "burcht": {
   "z": {},
   "l": [
    "51.2000",
    "4.3500"
   ]
  },
  "boekel": {
   "z": {},
   "l": [
    "51.1667",
    "4.9000"
   ]
  },
  "pulderbos": {
   "z": {
    "2242": [
     "51.2167",
     "4.6833"
    ]
   },
   "l": [
    "51.2167",
    "4.6833"
   ]
  },
  "gierle": {
   "z": {},
   "l": [
    "51.2667",
    "4.8500"
   ]
  },
  "schoorsche heide": {
   "z": {},
   "l": [
    "51.4500",
    "4.8000"
   ]
  },
  "wechelderzande": {
   "z": {},
   "l": [
    "51.2667",
    "4.7667"
   ]
  },
  "daussois": {
   "z": {},
   "l": [
    "50.2167",
    "4.4500"
   ]
  },
  "vremde": {
   "z": {
    "2531": [
     "51.1833",
     "4.5167"
    ]
   },
   "l": [
    "51.1833",
    "4.5167"
   ]
  },
  "viersel": {
   "z": {},
   "l": [
    "51.1833",
    "4.6333"
   ]
  },
  "beerzel": {
   "z": {},
   "l": [
    "51.0667",
    "4.6667"
   ]
  },
  "rymenam": {
   "z": {},
   "l": [
    "51.0000",
    "4.5667"
   ]
  },
  "blaasveld": {
   "z": {},
   "l": [
    "51.0500",
    "4.3667"
   ]
  },
  "heeze": {
   "z": {},
   "l": [
    "51.1500",
    "4.9333"
   ]
  },
  "vlimmeren": {
   "z": {},
   "l": [
    "51.3000",
    "4.7833"
   ]
  },
  "walem": {
   "z": {},
   "l": [
    "51.0667",
    "4.4667"
   ]
  },
  "loenhout": {
   "z": {},
   "l": [
    "51.4000",
    "4.6500"
   ]
  },
  "housie": {
   "z": {},
   "l": [
    "51.2500",
    "5.8333"
   ]
  },
  "tongerlo": {
   "z": {},
   "l": [
    "51.1167",
    "4.9000"
   ]
  },
  "zandvliet": {
   "z": {},
   "l": [
    "51.1500",
    "5.1333"
   ]
  },
  "eindhout": {
   "z": {},
   "l": [
    "51.1000",
    "5.0000"
   ]
  },
  "de dreef": {
   "z": {},
   "l": [
    "51.5000",
    "4.7833"
   ]
  },
  "hingene": {
   "z": {},
   "l": [
    "51.1000",
    "4.2667"
   ]
  },
  "pijpelheide": {
   "z": {},
   "l": [
    "51.0333",
    "4.7500"
   ]
  },
  "houtem": {
   "z": {},
   "l": [
    "51.2333",
    "4.9833"
   ]
  },
  "'s-gravenwezel": {
   "z": {},
   "l": [
    "51.2667",
    "4.5500"
   ]
  },
  "sint-job-in-'t-goor": {
   "z": {},
   "l": [
    "51.3000",
    "4.5833"
   ]
  },
  "houtvenne": {
   "z": {},
   "l": [
    "51.0500",
    "4.8000"
   ]
  },
  "lippelo": {
   "z": {},
   "l": [
    "51.0500",
    "4.2667"
   ]
  },
  "sint-mariaburg": {
   "z": {},
   "l": [
    "51.3000",
    "4.4333"
   ]
  },
  "ramsel": {
   "z": {
    "7524": [
     "51.0333",
     "4.8167"
    ]
   },
   "l": [
    "51.0333",
    "4.8167"
   ]
  },
  "bevel": {
   "z": {},
   "l": [
    "51.1333",
    "4.6833"
   ]
  },
  "sint-antonius": {
   "z": {},
   "l": [
    "51.2667",
    "4.6333"
   ]
  },
  "sint-lenaarts": {
   "z": {},
   "l": [
    "51.3500",
    "4.6833"
   ]
  },
  "massenhoven": {
   "z": {},
   "l": [
    "51.2000",
    "4.6167"
   ]
  },
  "mariekerke": {
   "z": {},
   "l": [
    "51.0667",
    "4.2000"
   ]
  },
  "noorderwijk": {
   "z": {},
   "l": [
    "51.1500",
    "4.8333"
   ]
  },
  "kalfort": {
   "z": {},
   "l": [
    "51.0667",
    "4.3000"
   ]
  },
  "heide": {
   "z": {},
   "l": [
    "51.1000",
    "4.3167"
   ]
  },
  "terhagen": {
   "z": {},
   "l": [
    "51.0833",
    "4.4000"
   ]
  },
  "aarle": {
   "z": {},
   "l": [
    "51.4833",
    "5.0167"
   ]
  },
  "pulle": {
   "z": {
    "2243": [
     "51.2000",
     "4.7000"
    ]
   },
   "l": [
    "51.2000",
    "4.7000"
   ]
  },
  "poederlee": {
   "z": {},
   "l": [
    "51.2333",
    "4.8167"
   ]
  },
  "looi": {
   "z": {},
   "l": [
    "51.3333",
    "4.7500"
   ]
  },
  "gestel": {
   "z": {},
   "l": [
    "51.1167",
    "5.1167"
   ]
  },
  "heindonk": {
   "z": {},
   "l": [
    "51.0667",
    "4.4000"
   ]
  },
  "kiel": {
   "z": {},
   "l": [
    "51.2000",
    "4.3833"
   ]
  },
  "gompel": {
   "z": {},
   "l": [
    "51.1833",
    "5.1667"
   ]
  },
  "boschkant": {
   "z": {},
   "l": [
    "51.0833",
    "4.2333"
   ]
  },
  "hout": {
   "z": {},
   "l": [
    "51.3333",
    "4.8333"
   ]
  },
  "liefkenshoek": {
   "z": {},
   "l": [
    "51.2333",
    "4.6333"
   ]
  },
  "anvers": {
   "z": {
    "9002": [
     "51.2167",
     "4.4167"
    ]
   },
   "l": [
    "51.2167",
    "4.4167"
   ]
  },
  "list": {
   "z": {},
   "l": [
    "51.2667",
    "4.4667"
   ]
  },
  "rooy": {
   "z": {},
   "l": [
    "51.1833",
    "4.4333"
   ]
  },
  "sept": {
   "z": {},
   "l": [
    "51.2667",
    "4.7833"
   ]
  },
  "moor": {
   "z": {},
   "l": [
    "51.1833",
    "4.5833"
   ]
  },
  "pierstraat": {
   "z": {},
   "l": [
    "51.1167",
    "4.4167"
   ]
  },
  "meeren": {
   "z": {},
   "l": [
    "51.1500",
    "4.9167"
   ]
  },
  "regenboog": {
   "z": {},
   "l": [
    "51.2167",
    "4.4667"
   ]
  },
  "cauwenberg": {
   "z": {},
   "l": [
    "51.2500",
    "4.8500"
   ]
  },
  "bos": {
   "z": {},
   "l": [
    "51.0667",
    "4.7167"
   ]
  },
  "gooreind": {
   "z": {},
   "l": [
    "51.2000",
    "4.9667"
   ]
  },
  "wildert": {
   "z": {},
   "l": [
    "51.3833",
    "5.0333"
   ]
  },
  "nieuwstraat": {
   "z": {},
   "l": [
    "51.1167",
    "5.0500"
   ]
  },
  "kruisweg": {
   "z": {},
   "l": [
    "51.0833",
    "4.4833"
   ]
  },
  "breendonck": {
   "z": {},
   "l": [
    "51.0500",
    "4.3333"
   ]
  },
  "willebroeck": {
   "z": {},
   "l": [
    "51.0667",
    "4.3667"
   ]
  },
  "schoonbroek": {
   "z": {},
   "l": [
    "51.2833",
    "5.0667"
   ]
  },
  "pullaar": {
   "z": {},
   "l": [
    "51.0667",
    "4.3333"
   ]
  },
  "vijfhuizen": {
   "z": {},
   "l": [
    "51.1000",
    "4.8667"
   ]
  },
  "madestraat": {
   "z": {},
   "l": [
    "51.0167",
    "4.8167"
   ]
  },
  "zurenborg": {
   "z": {},
   "l": [
    "51.2000",
    "4.4333"
   ]
  },
  "bel": {
   "z": {},
   "l": [
    "51.1667",
    "5.0667"
   ]
  },
  "plein": {
   "z": {},
   "l": [
    "51.0167",
    "4.4167"
   ]
  },
  "bergen": {
   "z": {},
   "l": [
    "51.1500",
    "4.7833"
   ]
  },
  "brand": {
   "z": {},
   "l": [
    "51.0500",
    "4.7833"
   ]
  },
  "zoerle-parwijs": {
   "z": {},
   "l": [
    "51.0833",
    "4.8667"
   ]
  },
  "brabant-putte": {
   "z": {},
   "l": [
    "51.3500",
    "4.3833"
   ]
  },
  "achterbos": {
   "z": {},
   "l": [
    "51.2000",
    "5.1000"
   ]
  },
  "sint-jozef-olen": {
   "z": {},
   "l": [
    "51.1833",
    "4.9000"
   ]
  },
  "pontfort": {
   "z": {},
   "l": [
    "51.2667",
    "5.0500"
   ]
  },
  "lierre": {
   "z": {},
   "l": [
    "51.1333",
    "4.5667"
   ]
  },
  "oosterwijk": {
   "z": {},
   "l": [
    "51.1333",
    "4.8667"
   ]
  },
  "hoge heide": {
   "z": {},
   "l": [
    "51.0833",
    "4.2167"
   ]
  },
  "hulsel": {
   "z": {},
   "l": [
    "51.4667",
    "5.0667"
   ]
  },
  "beulk": {
   "z": {},
   "l": [
    "51.2667",
    "4.7833"
   ]
  },
  "kapelleveld": {
   "z": {},
   "l": [
    "51.2167",
    "4.5167"
   ]
  },
  "broekstraat": {
   "z": {},
   "l": [
    "51.1000",
    "4.2500"
   ]
  },
  "meir": {
   "z": {},
   "l": [
    "51.0667",
    "4.2500"
   ]
  },
  "stelen": {
   "z": {},
   "l": [
    "51.1333",
    "4.9667"
   ]
  },
  "grasheide": {
   "z": {},
   "l": [
    "51.0333",
    "4.6500"
   ]
  },
  "allierscheheide": {
   "z": {},
   "l": [
    "51.1500",
    "4.5667"
   ]
  },
  "kruikeven": {
   "z": {},
   "l": [
    "51.3500",
    "5.1167"
   ]
  },
  "limberg": {
   "z": {},
   "l": [
    "51.0500",
    "4.8667"
   ]
  },
  "ongelberg": {
   "z": {},
   "l": [
    "51.1667",
    "5.2000"
   ]
  },
  "nieuwmoer": {
   "z": {},
   "l": [
    "51.4333",
    "4.5167"
   ]
  },
  "molenstraat": {
   "z": {},
   "l": [
    "51.1000",
    "4.3833"
   ]
  },
  "eerselingen": {
   "z": {},
   "l": [
    "51.2000",
    "4.9167"
   ]
  },
  "demer": {
   "z": {},
   "l": [
    "51.0333",
    "4.8833"
   ]
  },
  "heieinde": {
   "z": {},
   "l": [
    "51.0500",
    "4.9667"
   ]
  },
  "keer": {
   "z": {},
   "l": [
    "51.2167",
    "4.5333"
   ]
  },
  "heiken": {
   "z": {},
   "l": [
    "51.0500",
    "4.2167"
   ]
  },
  "beel": {
   "z": {},
   "l": [
    "51.1667",
    "5.0667"
   ]
  },
  "truitseinde": {
   "z": {},
   "l": [
    "51.0167",
    "4.8500"
   ]
  },
  "luchtbal": {
   "z": {},
   "l": [
    "51.2500",
    "4.4167"
   ]
  },
  "postel": {
   "z": {},
   "l": [
    "51.2833",
    "5.2000"
   ]
  },
  "leemputten": {
   "z": {},
   "l": [
    "51.0833",
    "4.6667"
   ]
  },
  "lochtenberg": {
   "z": {},
   "l": [
    "51.3000",
    "4.5667"
   ]
  },
  "voortkapel": {
   "z": {},
   "l": [
    "51.1167",
    "4.8500"
   ]
  },
  "kimpelberg": {
   "z": {},
   "l": [
    "51.0667",
    "4.2833"
   ]
  },
  "kattenberg": {
   "z": {},
   "l": [
    "51.2500",
    "4.6333"
   ]
  },
  "mol ter neet": {
   "z": {},
   "l": [
    "51.1667",
    "4.6333"
   ]
  },
  "heultje": {
   "z": {},
   "l": [
    "51.0833",
    "4.8333"
   ]
  },
  "horendonck": {
   "z": {},
   "l": [
    "51.4667",
    "4.5000"
   ]
  },
  "sainte-anne": {
   "z": {},
   "l": [
    "51.2167",
    "4.3833"
   ]
  },
  "malines": {
   "z": {},
   "l": [
    "51.0333",
    "4.4667"
   ]
  },
  "het nieuwland": {
   "z": {},
   "l": [
    "51.2667",
    "5.1833"
   ]
  },
  "most": {
   "z": {},
   "l": [
    "51.1667",
    "5.2500"
   ]
  },
  "groenstraat": {
   "z": {},
   "l": [
    "51.1333",
    "4.8167"
   ]
  },
  "oude baan": {
   "z": {},
   "l": [
    "51.2500",
    "4.6000"
   ]
  },
  "waasdonk": {
   "z": {},
   "l": [
    "51.1833",
    "4.4500"
   ]
  },
  "bremstraat": {
   "z": {},
   "l": [
    "51.2500",
    "4.4500"
   ]
  },
  "varendonk": {
   "z": {},
   "l": [
    "51.0667",
    "4.9333"
   ]
  },
  "dreef": {
   "z": {},
   "l": [
    "51.5000",
    "4.7833"
   ]
  },
  "larendries": {
   "z": {},
   "l": [
    "51.0500",
    "4.2167"
   ]
  },
  "schoten-heide-bad": {
   "z": {},
   "l": [
    "51.3000",
    "4.5333"
   ]
  },
  "steenbergen": {
   "z": {},
   "l": [
    "51.0833",
    "5.0000"
   ]
  },
  "de kluis": {
   "z": {},
   "l": [
    "51.2500",
    "4.5667"
   ]
  },
  "maria-ter-heide": {
   "z": {},
   "l": [
    "51.3167",
    "4.5167"
   ]
  },
  "steenhoven": {
   "z": {},
   "l": [
    "51.3000",
    "4.7000"
   ]
  },
  "bergom": {
   "z": {},
   "l": [
    "51.0667",
    "4.9167"
   ]
  },
  "bouchout": {
   "z": {},
   "l": [
    "51.1667",
    "4.5000"
   ]
  },
  "hallaar": {
   "z": {},
   "l": [
    "51.0833",
    "4.7167"
   ]
  },
  "klein willebroek": {
   "z": {},
   "l": [
    "51.0833",
    "4.3667"
   ]
  },
  "heerle": {
   "z": {},
   "l": [
    "51.2167",
    "4.8667"
   ]
  },
  "opstal": {
   "z": {},
   "l": [
    "51.2500",
    "4.9000"
   ]
  },
  "zonderschot": {
   "z": {},
   "l": [
    "51.0667",
    "4.7333"
   ]
  },
  "seggen": {
   "z": {},
   "l": [
    "51.2000",
    "4.9333"
   ]
  },
  "de steenhoeven": {
   "z": {},
   "l": [
    "51.2667",
    "4.6167"
   ]
  },
  "oorderen": {
   "z": {},
   "l": [
    "51.2833",
    "4.3667"
   ]
  },
  "de kwikaard": {
   "z": {},
   "l": [
    "51.2833",
    "4.6000"
   ]
  },
  "de hand": {
   "z": {},
   "l": [
    "51.1000",
    "4.8500"
   ]
  },
  "sint-antoniushoek": {
   "z": {},
   "l": [
    "51.2833",
    "4.2500"
   ]
  },
  "het kamp": {
   "z": {},
   "l": [
    "51.2833",
    "4.6167"
   ]
  },
  "kalishoek": {
   "z": {},
   "l": [
    "51.2833",
    "4.2667"
   ]
  },
  "withof": {
   "z": {},
   "l": [
    "51.3333",
    "4.5167"
   ]
  },
  "halle": {
   "z": {},
   "l": [
    "51.2333",
    "4.6333"
   ]
  },
  "bethania": {
   "z": {},
   "l": [
    "51.3167",
    "4.5167"
   ]
  },
  "saint-job-in 't-goor": {
   "z": {},
   "l": [
    "51.3000",
    "4.5833"
   ]
  },
  "tremelheide": {
   "z": {},
   "l": [
    "51.3167",
    "4.5833"
   ]
  },
  "meerlaar": {
   "z": {},
   "l": [
    "51.0833",
    "5.0500"
   ]
  },
  "saint-amand": {
   "z": {},
   "l": [
    "51.0500",
    "4.2000"
   ]
  },
  "beek": {
   "z": {},
   "l": [
    "51.2333",
    "4.8333"
   ]
  },
  "laar": {
   "z": {},
   "l": [
    "51.0667",
    "4.7500"
   ]
  },
  "lillo": {
   "z": {},
   "l": [
    "51.1500",
    "4.7000"
   ]
  },
  "horendonk": {
   "z": {},
   "l": [
    "51.4667",
    "4.5000"
   ]
  },
  "donk": {
   "z": {},
   "l": [
    "51.1333",
    "4.5500"
   ]
  },
  "drijhoek": {
   "z": {},
   "l": [
    "51.2500",
    "4.6333"
   ]
  },
  "locht": {
   "z": {},
   "l": [
    "51.0833",
    "4.8333"
   ]
  },
  "gilseinde": {
   "z": {},
   "l": [
    "51.3667",
    "5.0000"
   ]
  },
  "oolen": {
   "z": {},
   "l": [
    "51.1500",
    "4.8500"
   ]
  },
  "klein vorst": {
   "z": {},
   "l": [
    "51.0833",
    "5.0667"
   ]
  },
  "kruisstraat": {
   "z": {},
   "l": [
    "51.3667",
    "4.5000"
   ]
  },
  "millegem": {
   "z": {},
   "l": [
    "51.1833",
    "4.5500"
   ]
  },
  "dries": {
   "z": {},
   "l": [
    "51.0667",
    "4.6667"
   ]
  },
  "merxem": {
   "z": {},
   "l": [
    "51.2500",
    "4.4500"
   ]
  },
  "lokeren": {
   "z": {},
   "l": [
    "51.3167",
    "4.9333"
   ]
  },
  "zammel": {
   "z": {},
   "l": [
    "51.1000",
    "4.9500"
   ]
  }
 },
 "l": [
  "51.2167",
  "4.4167"
 ]
}