{
 "c": {
  "laem": {
   "z": {},
   "l": [
    "13.2047",
    "99.9796"
   ]
  },
  "phetchaburi": {
   "z": {
    "76000": [
     "13.0694",
     "100.0528"
    ],
    "76110": [
     "13.2167",
     "99.9833"
    ],
    "76120": [
     "12.8000",
     "99.9667"
    ],
    "76130": [
     "13.1119",
     "99.9447"
    ],
    "76150": [
     "13.1119",
     "99.9447"
    ]
   },
   "l": [
    "13.1119",
    "99.9447"
   ]
  },
  "ban pak khlong": {
   "z": {},
   "l": [
    "12.8667",
    "100.0167"
   ]
  },
  "khao yoi": {
   "z": {},
   "l": [
    "13.2167",
    "99.8333"
   ]
  },
  "cha-am": {
   "z": {},
   "l": [
    "12.8000",
    "99.9667"
   ]
  },
  "nong chok": {
   "z": {},
   "l": [
    "12.9500",
    "99.9667"
   ]
  },
  "amphoe ban laem": {
   "z": {},
   "l": [
    "13.2167",
    "99.9833"
   ]
  },
  "ban pong": {
   "z": {},
   "l": [
    "13.0500",
    "99.8667"
   ]
  },
  "ban huai sai tai": {
   "z": {},
   "l": [
    "12.6833",
    "99.9500"
   ]
  },
  "amphoe khao yoi": {
   "z": {},
   "l": [
    "13.2402",
    "99.8243"
   ]
  },
  "petchaburi": {
   "z": {
    "6676120": [
     "13.1119",
     "99.9447"
    ]
   },
   "l": [
    "13.1119",
    "99.9447"
   ]
  },
  "ban lat": {
   "z": {},
   "l": [
    "13.0500",
    "99.9191"
   ]
  },
  "ban nong khao nok": {
   "z": {},
   "l": [
    "12.6667",
    "99.9000"
   ]
  },
  "muang pecha buri": {
   "z": {},
   "l": [
    "13.1119",
    "99.9447"
   ]
  },
  "amphoe ban lat": {
   "z": {},
   "l": [
    "13.0500",
    "99.9191"
   ]
  },
  "ban laem": {
   "z": {},
   "l": [
    "13.2047",
    "99.9796"
   ]
  },
  "ban hua khoi": {
   "z": {},
   "l": [
    "13.1167",
    "99.9833"
   ]
  },
  "ban nai ban": {
   "z": {},
   "l": [
    "13.0667",
    "100.0000"
   ]
  }
 },
 "l": [
  "13.1119",
  "99.9447"
 ]
}