{
 "c": {
  "sojadibawah": {
   "z": {},
   "l": [
    "-3.7089",
    "128.2007"
   ]
  },
  "langgur": {
   "z": {},
   "l": [
    "-5.6667",
    "132.7167"
   ]
  },
  "ambon": {
   "z": {
    "97117": [
     "-3.6954",
     "128.1814"
    ],
    "97128": [
     "-3.6954",
     "128.1814"
    ],
    "97231": [
     "-3.6954",
     "128.1814"
    ]
   },
   "l": [
    "-3.6954",
    "128.1814"
   ]
  },
  "timur": {
   "z": {},
   "l": [
    "-8.1833",
    "131.0833"
   ]
  },
  "said": {
   "z": {},
   "l": [
    "-3.5940",
    "128.0341"
   ]
  }
 },
 "l": []
}