{
 "c": {
  "lewiston": {
   "z": {
    "04240": [
     "44.0845",
     "-70.1696"
    ],
    "04243": [
     "44.1003",
     "-70.2148"
    ],
    "04241": [
     "44.1003",
     "-70.2148"
    ]
   },
   "l": [
    "44.1003",
    "-70.2148"
   ]
  },
  "bangor": {
   "z": {
    "04401": [
     "44.8635",
     "-68.8402"
    ],
    "04402": [
     "44.8012",
     "-68.7778"
    ]
   },
   "l": [
    "44.8012",
    "-68.7778"
   ]
  },
  "madison": {
   "z": {
    "04950": [
     "44.8351",
     "-69.8050"
    ]
   },
   "l": []
  },
  "rockport": {
   "z": {
    "04856": [
     "44.1733",
     "-69.1248"
    ]
   },
   "l": []
  },
  "york": {
   "z": {
    "03909": [
     "43.1637",
     "-70.6750"
    ]
   },
   "l": []
  },
  "south portland": {
   "z": {
    "04106": [
     "43.6253",
     "-70.2955"
    ],
    "04116": [
     "43.6415",
     "-70.2409"
    ]
   },
   "l": [
    "43.6415",
    "-70.2409"
   ]
  },
  "falmouth": {
   "z": {
    "04105": [
     "43.7516",
     "-70.2793"
    ]
   },
   "l": []
  },
  "burnham": {
   "z": {
    "04922": [
     "44.6929",
     "-69.3846"
    ]
   },
   "l": []
  },
  "yarmouth": {
   "z": {
    "04096": [
     "43.8172",
     "-70.1783"
    ]
   },
   "l": []
  },
  "portland": {
   "z": {
    "04101": [
     "43.6589",
     "-70.2615"
    ],
    "04102": [
     "43.6636",
     "-70.3027"
    ],
    "04103": [
     "43.6948",
     "-70.2905"
    ],
    "04104": [
     "43.6615",
     "-70.2553"
    ],
    "04112": [
     "43.6615",
     "-70.2553"
    ],
    "04109": [
     "43.6783",
     "-70.1987"
    ],
    "04122": [
     "44.4081",
     "-70.4707"
    ],
    "04123": [
     "44.4081",
     "-70.4707"
    ]
   },
   "l": [
    "43.6615",
    "-70.2553"
   ]
  },
  "rockland": {
   "z": {
    "04841": [
     "44.1272",
     "-69.1336"
    ]
   },
   "l": []
  },
  "gardiner": {
   "z": {
    "04345": [
     "44.2168",
     "-69.8522"
    ]
   },
   "l": []
  },
  "westbrook": {
   "z": {
    "04092": [
     "43.7150",
     "-70.3452"
    ],
    "04098": [
     "43.6770",
     "-70.3712"
    ]
   },
   "l": [
    "43.6770",
    "-70.3712"
   ]
  },
  "clinton": {
   "z": {
    "04927": [
     "44.6714",
     "-69.5375"
    ]
   },
   "l": []
  },
  "old town": {
   "z": {
    "04468": [
     "45.0360",
     "-68.7327"
    ]
   },
   "l": []
  },
  "caribou": {
   "z": {
    "04736": [
     "46.9121",
     "-68.0431"
    ]
   },
   "l": []
  },
  "waldoboro": {
   "z": {
    "04572": [
     "44.1085",
     "-69.3659"
    ]
   },
   "l": []
  },
  "kennebunk": {
   "z": {
    "04043": [
     "43.3972",
     "-70.5722"
    ]
   },
   "l": []
  },
  "auburn": {
   "z": {
    "04210": [
     "44.0861",
     "-70.2434"
    ],
    "04212": [
     "44.0979",
     "-70.2312"
    ],
    "04211": [
     "44.0979",
     "-70.2312"
    ]
   },
   "l": [
    "44.0979",
    "-70.2312"
   ]
  },
  "brunswick": {
   "z": {
    "04011": [
     "43.8988",
     "-69.9725"
    ]
   },
   "l": []
  },
  "brooksville": {
   "z": {
    "04617": [
     "44.3667",
     "-68.7454"
    ]
   },
   "l": []
  },
  "belfast": {
   "z": {
    "04915": [
     "44.4735",
     "-69.0551"
    ]
   },
   "l": []
  },
  "stockton springs": {
   "z": {
    "04981": [
     "44.5211",
     "-68.8704"
    ]
   },
   "l": []
  },
  "scarborough": {
   "z": {
    "04074": [
     "43.5923",
     "-70.3735"
    ],
    "04070": [
     "43.5781",
     "-70.3217"
    ]
   },
   "l": [
    "43.5781",
    "-70.3217"
   ]
  },
  "sanford": {
   "z": {
    "04073": [
     "43.4042",
     "-70.7455"
    ]
   },
   "l": []
  },
  "augusta": {
   "z": {
    "04330": [
     "44.4051",
     "-69.7567"
    ],
    "04333": [
     "44.4141",
     "-69.7519"
    ],
    "04336": [
     "44.3157",
     "-69.8180"
    ],
    "04338": [
     "44.3106",
     "-69.7795"
    ],
    "04332": [
     "44.3106",
     "-69.7795"
    ]
   },
   "l": [
    "44.3106",
    "-69.7795"
   ]
  },
  "madawaska": {
   "z": {
    "04756": [
     "47.3163",
     "-68.3007"
    ]
   },
   "l": []
  },
  "fort kent": {
   "z": {
    "04743": [
     "47.1923",
     "-68.4824"
    ]
   },
   "l": []
  },
  "guilford": {
   "z": {
    "04443": [
     "45.2677",
     "-69.3302"
    ]
   },
   "l": []
  },
  "sedgwick": {
   "z": {
    "04676": [
     "44.3502",
     "-68.6434"
    ]
   },
   "l": []
  },
  "camden": {
   "z": {
    "04843": [
     "44.2253",
     "-69.0923"
    ]
   },
   "l": []
  },
  "harborside": {
   "z": {
    "04642": [
     "44.3341",
     "-68.8091"
    ]
   },
   "l": []
  },
  "new gloucester": {
   "z": {
    "04260": [
     "43.9564",
     "-70.3024"
    ]
   },
   "l": []
  },
  "millinocket": {
   "z": {
    "04462": [
     "45.7226",
     "-68.7951"
    ]
   },
   "l": []
  },
  "brewer": {
   "z": {
    "04412": [
     "44.7807",
     "-68.7351"
    ]
   },
   "l": []
  },
  "nobleboro": {
   "z": {
    "04555": [
     "44.1109",
     "-69.4820"
    ]
   },
   "l": []
  },
  "newport": {
   "z": {
    "04953": [
     "44.8595",
     "-69.2346"
    ]
   },
   "l": []
  },
  "fairfield": {
   "z": {
    "04937": [
     "44.6370",
     "-69.6804"
    ]
   },
   "l": []
  },
  "kittery": {
   "z": {
    "03904": [
     "43.1153",
     "-70.7051"
    ]
   },
   "l": []
  },
  "skowhegan": {
   "z": {
    "04976": [
     "44.8071",
     "-69.6740"
    ]
   },
   "l": []
  },
  "presque isle": {
   "z": {
    "04769": [
     "46.6885",
     "-67.9911"
    ]
   },
   "l": []
  },
  "parsonsfield": {
   "z": {
    "04047": [
     "43.7421",
     "-70.9141"
    ]
   },
   "l": []
  },
  "bridgton": {
   "z": {
    "04009": [
     "44.0336",
     "-70.7570"
    ]
   },
   "l": []
  },
  "pittsfield": {
   "z": {
    "04967": [
     "44.7695",
     "-69.4283"
    ]
   },
   "l": []
  },
  "biddeford": {
   "z": {
    "04005": [
     "43.4961",
     "-70.4886"
    ],
    "04007": [
     "43.4926",
     "-70.4534"
    ]
   },
   "l": [
    "43.4926",
    "-70.4534"
   ]
  },
  "dexter": {
   "z": {
    "04930": [
     "45.0292",
     "-69.3164"
    ]
   },
   "l": []
  },
  "poland": {
   "z": {
    "04274": [
     "44.0452",
     "-70.3871"
    ]
   },
   "l": []
  },
  "unity": {
   "z": {
    "04988": [
     "44.5994",
     "-69.3406"
    ]
   },
   "l": []
  },
  "deer isle": {
   "z": {
    "04627": [
     "44.2237",
     "-68.6487"
    ]
   },
   "l": []
  },
  "brooklin": {
   "z": {
    "04616": [
     "44.2855",
     "-68.5727"
    ]
   },
   "l": []
  },
  "phippsburg": {
   "z": {
    "04562": [
     "43.7900",
     "-69.8271"
    ]
   },
   "l": []
  },
  "hampden": {
   "z": {
    "04444": [
     "44.7238",
     "-68.9319"
    ]
   },
   "l": []
  },
  "orono": {
   "z": {
    "04469": [
     "45.0028",
     "-68.6334"
    ],
    "04473": [
     "44.8791",
     "-68.7330"
    ]
   },
   "l": [
    "44.8831",
    "-68.6720"
   ]
  },
  "limestone": {
   "z": {
    "04751": [
     "46.8929",
     "-67.9643"
    ],
    "04750": [
     "46.9582",
     "-67.8598"
    ]
   },
   "l": [
    "46.9087",
    "-67.8259"
   ]
  },
  "waterville": {
   "z": {
    "04901": [
     "44.5616",
     "-69.5559"
    ],
    "04903": [
     "44.5520",
     "-69.6317"
    ]
   },
   "l": [
    "44.5520",
    "-69.6317"
   ]
  },
  "wells": {
   "z": {
    "04090": [
     "43.3199",
     "-70.6318"
    ]
   },
   "l": []
  },
  "gorham": {
   "z": {
    "04038": [
     "43.7224",
     "-70.4622"
    ]
   },
   "l": []
  },
  "eliot": {
   "z": {
    "03903": [
     "43.1466",
     "-70.7830"
    ]
   },
   "l": []
  },
  "bath": {
   "z": {
    "04530": [
     "43.9030",
     "-69.8506"
    ]
   },
   "l": []
  },
  "kennebunkport": {
   "z": {
    "04046": [
     "43.4183",
     "-70.4984"
    ]
   },
   "l": []
  },
  "bar harbor": {
   "z": {
    "04609": [
     "44.3761",
     "-68.2757"
    ]
   },
   "l": []
  },
  "ellsworth": {
   "z": {
    "04605": [
     "44.6513",
     "-68.4507"
    ]
   },
   "l": []
  },
  "wiscasset": {
   "z": {
    "04578": [
     "44.0100",
     "-69.6871"
    ]
   },
   "l": []
  },
  "bethel": {
   "z": {
    "04217": [
     "44.3677",
     "-70.8352"
    ]
   },
   "l": []
  },
  "gray": {
   "z": {
    "04039": [
     "43.8876",
     "-70.3505"
    ]
   },
   "l": []
  },
  "fort fairfield": {
   "z": {
    "04742": [
     "46.7793",
     "-67.8573"
    ]
   },
   "l": []
  },
  "saco": {
   "z": {
    "04072": [
     "43.5416",
     "-70.4687"
    ]
   },
   "l": []
  },
  "oakland": {
   "z": {
    "04963": [
     "44.5668",
     "-69.8822"
    ]
   },
   "l": []
  },
  "buckfield": {
   "z": {
    "04220": [
     "44.2997",
     "-70.3698"
    ]
   },
   "l": []
  },
  "new portland": {
   "z": {
    "04961": [
     "45.1008",
     "-70.0842"
    ],
    "04954": [
     "44.8907",
     "-70.0626"
    ]
   },
   "l": [
    "44.8842",
    "-70.0967"
   ]
  },
  "houlton": {
   "z": {
    "04730": [
     "46.1154",
     "-67.9170"
    ]
   },
   "l": []
  },
  "columbia falls": {
   "z": {
    "04623": [
     "44.7189",
     "-67.7349"
    ]
   },
   "l": []
  },
  "berwick": {
   "z": {
    "03901": [
     "43.3048",
     "-70.8421"
    ]
   },
   "l": []
  },
  "alfred": {
   "z": {
    "04002": [
     "43.4958",
     "-70.6841"
    ]
   },
   "l": []
  },
  "lebanon": {
   "z": {
    "04027": [
     "43.3997",
     "-70.9007"
    ]
   },
   "l": []
  },
  "freeport": {
   "z": {
    "04032": [
     "43.8635",
     "-70.0976"
    ],
    "04033": [
     "44.4081",
     "-70.4707"
    ],
    "04034": [
     "44.4081",
     "-70.4707"
    ]
   },
   "l": [
    "43.8570",
    "-70.1031"
   ]
  },
  "denmark": {
   "z": {
    "04022": [
     "43.9813",
     "-70.8063"
    ]
   },
   "l": []
  },
  "seal harbor": {
   "z": {
    "04675": [
     "44.3031",
     "-68.2403"
    ]
   },
   "l": []
  },
  "windham": {
   "z": {
    "04062": [
     "43.7940",
     "-70.3979"
    ]
   },
   "l": []
  },
  "jefferson": {
   "z": {
    "04348": [
     "44.2220",
     "-69.5088"
    ]
   },
   "l": []
  },
  "stillwater": {
   "z": {
    "04489": [
     "44.9084",
     "-68.6864"
    ]
   },
   "l": []
  },
  "standish": {
   "z": {
    "04084": [
     "43.7667",
     "-70.5559"
    ]
   },
   "l": []
  },
  "georgetown": {
   "z": {
    "04548": [
     "43.8176",
     "-69.7156"
    ]
   },
   "l": []
  },
  "south paris": {
   "z": {
    "04281": [
     "44.2438",
     "-70.4905"
    ]
   },
   "l": []
  },
  "winthrop": {
   "z": {
    "04364": [
     "44.3131",
     "-69.9645"
    ]
   },
   "l": []
  },
  "greene": {
   "z": {
    "04236": [
     "44.1921",
     "-70.1442"
    ]
   },
   "l": []
  },
  "cape elizabeth": {
   "z": {
    "04107": [
     "43.5932",
     "-70.2382"
    ]
   },
   "l": []
  },
  "belgrade": {
   "z": {
    "04917": [
     "44.4876",
     "-69.8380"
    ]
   },
   "l": []
  },
  "southport": {
   "z": {
    "04576": [
     "43.8187",
     "-69.6696"
    ]
   },
   "l": []
  },
  "milbridge": {
   "z": {
    "04658": [
     "44.5685",
     "-67.8656"
    ]
   },
   "l": []
  },
  "north bridgton": {
   "z": {
    "04057": [
     "44.0987",
     "-70.6987"
    ]
   },
   "l": []
  },
  "castine": {
   "z": {
    "04420": [
     "44.4130",
     "-68.7980"
    ],
    "04421": [
     "44.4168",
     "-68.7940"
    ]
   },
   "l": [
    "44.3879",
    "-68.7998"
   ]
  },
  "south berwick": {
   "z": {
    "03908": [
     "43.2418",
     "-70.7400"
    ]
   },
   "l": []
  },
  "albion": {
   "z": {
    "04910": [
     "44.5519",
     "-69.4438"
    ]
   },
   "l": []
  },
  "baileyville": {
   "z": {
    "04694": [
     "45.1285",
     "-67.4510"
    ]
   },
   "l": []
  },
  "lincoln": {
   "z": {
    "04457": [
     "45.4580",
     "-68.4812"
    ]
   },
   "l": []
  },
  "vinalhaven": {
   "z": {
    "04863": [
     "44.0815",
     "-68.8445"
    ]
   },
   "l": []
  },
  "springvale": {
   "z": {
    "04083": [
     "43.4589",
     "-70.8215"
    ]
   },
   "l": []
  },
  "east wilton": {
   "z": {
    "04234": [
     "44.6159",
     "-70.1928"
    ]
   },
   "l": []
  },
  "farmingdale": {
   "z": {
    "04344": [
     "44.2618",
     "-69.8232"
    ]
   },
   "l": []
  },
  "topsham": {
   "z": {
    "04086": [
     "43.9602",
     "-69.9654"
    ]
   },
   "l": []
  },
  "wilton": {
   "z": {
    "04294": [
     "44.6273",
     "-70.2567"
    ]
   },
   "l": []
  },
  "richmond": {
   "z": {
    "04357": [
     "44.1234",
     "-69.8319"
    ]
   },
   "l": []
  },
  "peaks island": {
   "z": {
    "04108": [
     "43.6623",
     "-70.1886"
    ]
   },
   "l": []
  },
  "bowdoinham": {
   "z": {
    "04008": [
     "44.0387",
     "-69.8684"
    ]
   },
   "l": []
  },
  "rumford": {
   "z": {
    "04276": [
     "44.5513",
     "-70.6366"
    ]
   },
   "l": []
  },
  "hallowell": {
   "z": {
    "04347": [
     "44.2882",
     "-69.8169"
    ]
   },
   "l": []
  },
  "manchester": {
   "z": {
    "04351": [
     "44.3296",
     "-69.8647"
    ]
   },
   "l": []
  },
  "carmel": {
   "z": {
    "04419": [
     "44.7979",
     "-69.0142"
    ]
   },
   "l": []
  },
  "old orchard beach": {
   "z": {
    "04064": [
     "43.5273",
     "-70.3894"
    ]
   },
   "l": []
  },
  "vassalboro": {
   "z": {
    "04989": [
     "44.4291",
     "-69.6471"
    ]
   },
   "l": []
  },
  "dover foxcroft": {
   "z": {
    "04426": [
     "45.2287",
     "-69.1492"
    ]
   },
   "l": []
  },
  "windsor": {
   "z": {
    "04363": [
     "44.3114",
     "-69.5785"
    ]
   },
   "l": []
  },
  "west newfield": {
   "z": {
    "04095": [
     "43.6273",
     "-70.9075"
    ]
   },
   "l": []
  },
  "searsport": {
   "z": {
    "04974": [
     "44.4967",
     "-68.9222"
    ]
   },
   "l": []
  },
  "mount vernon": {
   "z": {
    "04352": [
     "44.4709",
     "-69.9644"
    ]
   },
   "l": []
  },
  "naples": {
   "z": {
    "04055": [
     "43.9695",
     "-70.6168"
    ]
   },
   "l": []
  },
  "eagle lake": {
   "z": {
    "04739": [
     "47.0314",
     "-68.6420"
    ]
   },
   "l": []
  },
  "blue hill": {
   "z": {
    "04614": [
     "44.4264",
     "-68.5909"
    ]
   },
   "l": []
  },
  "calais": {
   "z": {
    "04619": [
     "45.1317",
     "-67.2209"
    ]
   },
   "l": []
  },
  "cumberland foreside": {
   "z": {
    "04110": [
     "43.7607",
     "-70.1964"
    ]
   },
   "l": []
  },
  "milo": {
   "z": {
    "04463": [
     "45.2004",
     "-68.9377"
    ]
   },
   "l": []
  },
  "edgecomb": {
   "z": {
    "04556": [
     "43.9746",
     "-69.6235"
    ]
   },
   "l": []
  },
  "chebeague island": {
   "z": {
    "04017": [
     "43.7330",
     "-70.1180"
    ]
   },
   "l": []
  },
  "aurora": {
   "z": {
    "04408": [
     "44.8636",
     "-68.2351"
    ]
   },
   "l": []
  },
  "kittery point": {
   "z": {
    "03905": [
     "43.0922",
     "-70.6867"
    ]
   },
   "l": []
  },
  "mount desert": {
   "z": {
    "04660": [
     "44.3422",
     "-68.3526"
    ]
   },
   "l": []
  },
  "north berwick": {
   "z": {
    "03906": [
     "43.3433",
     "-70.7839"
    ]
   },
   "l": []
  },
  "east machias": {
   "z": {
    "04630": [
     "44.7791",
     "-67.4273"
    ]
   },
   "l": []
  },
  "eddington": {
   "z": {
    "04428": [
     "44.8066",
     "-68.5728"
    ]
   },
   "l": []
  },
  "prospect harbor": {
   "z": {
    "04669": [
     "44.4286",
     "-68.0052"
    ]
   },
   "l": []
  },
  "mars hill": {
   "z": {
    "04758": [
     "46.5265",
     "-67.8470"
    ]
   },
   "l": []
  },
  "topsfield": {
   "z": {
    "04490": [
     "45.4351",
     "-67.7849"
    ]
   },
   "l": []
  },
  "kents hill": {
   "z": {
    "04349": [
     "44.4354",
     "-70.0731"
    ]
   },
   "l": []
  },
  "lisbon falls": {
   "z": {
    "04252": [
     "44.0250",
     "-70.0609"
    ]
   },
   "l": []
  },
  "greenville": {
   "z": {
    "04441": [
     "45.5296",
     "-69.3697"
    ]
   },
   "l": []
  },
  "farmington": {
   "z": {
    "04938": [
     "44.6536",
     "-70.1149"
    ]
   },
   "l": []
  },
  "ashland": {
   "z": {
    "04732": [
     "46.6077",
     "-68.4102"
    ]
   },
   "l": []
  },
  "machiasport": {
   "z": {
    "04655": [
     "44.6540",
     "-67.4015"
    ]
   },
   "l": []
  },
  "mexico": {
   "z": {
    "04257": [
     "44.5710",
     "-70.5120"
    ]
   },
   "l": []
  },
  "machias": {
   "z": {
    "04654": [
     "44.7986",
     "-67.5424"
    ]
   },
   "l": []
  },
  "jonesport": {
   "z": {
    "04649": [
     "44.5794",
     "-67.6002"
    ]
   },
   "l": []
  },
  "lisbon": {
   "z": {
    "04250": [
     "44.0271",
     "-70.1175"
    ]
   },
   "l": []
  },
  "waterboro": {
   "z": {
    "04087": [
     "43.5657",
     "-70.7504"
    ]
   },
   "l": []
  },
  "winter harbor": {
   "z": {
    "04693": [
     "44.3779",
     "-68.0578"
    ]
   },
   "l": []
  },
  "west rockport": {
   "z": {
    "04865": [
     "44.1820",
     "-69.1353"
    ]
   },
   "l": []
  },
  "newcastle": {
   "z": {
    "04553": [
     "44.0438",
     "-69.5675"
    ]
   },
   "l": []
  },
  "west kennebunk": {
   "z": {
    "04094": [
     "43.4087",
     "-70.5814"
    ]
   },
   "l": []
  },
  "cherryfield": {
   "z": {
    "04622": [
     "44.7111",
     "-67.9723"
    ]
   },
   "l": []
  },
  "bucksport": {
   "z": {
    "04416": [
     "44.6444",
     "-68.7402"
    ]
   },
   "l": []
  },
  "jay": {
   "z": {
    "04239": [
     "44.5317",
     "-70.2164"
    ]
   },
   "l": []
  },
  "penobscot": {
   "z": {
    "04476": [
     "44.4523",
     "-68.6865"
    ]
   },
   "l": []
  },
  "casco": {
   "z": {
    "04015": [
     "43.9742",
     "-70.5161"
    ]
   },
   "l": []
  },
  "oxford": {
   "z": {
    "04270": [
     "44.1032",
     "-70.5080"
    ]
   },
   "l": []
  },
  "damariscotta": {
   "z": {
    "04543": [
     "44.0357",
     "-69.4928"
    ]
   },
   "l": []
  },
  "sangerville": {
   "z": {
    "04479": [
     "45.1263",
     "-69.3065"
    ]
   },
   "l": []
  },
  "charleston": {
   "z": {
    "04422": [
     "45.0736",
     "-69.0343"
    ]
   },
   "l": []
  },
  "greenbush": {
   "z": {
    "04418": [
     "45.0838",
     "-68.4655"
    ]
   },
   "l": []
  },
  "steep falls": {
   "z": {
    "04085": [
     "43.7562",
     "-70.6190"
    ]
   },
   "l": []
  },
  "boothbay": {
   "z": {
    "04537": [
     "43.9034",
     "-69.6203"
    ]
   },
   "l": []
  },
  "warren": {
   "z": {
    "04864": [
     "44.1235",
     "-69.2410"
    ]
   },
   "l": []
  },
  "hartland": {
   "z": {
    "04943": [
     "44.8911",
     "-69.5287"
    ]
   },
   "l": []
  },
  "palmyra": {
   "z": {
    "04965": [
     "44.8466",
     "-69.3654"
    ]
   },
   "l": []
  },
  "jonesboro": {
   "z": {
    "04648": [
     "44.6683",
     "-67.5862"
    ]
   },
   "l": []
  },
  "etna": {
   "z": {
    "04434": [
     "44.7853",
     "-69.1349"
    ]
   },
   "l": []
  },
  "phillips": {
   "z": {
    "04966": [
     "44.8427",
     "-70.4368"
    ]
   },
   "l": []
  },
  "exeter": {
   "z": {
    "04435": [
     "44.9638",
     "-69.1354"
    ]
   },
   "l": []
  },
  "kingfield": {
   "z": {
    "04947": [
     "45.0293",
     "-70.2579"
    ]
   },
   "l": []
  },
  "solon": {
   "z": {
    "04979": [
     "44.9435",
     "-69.8071"
    ]
   },
   "l": []
  },
  "saint albans": {
   "z": {
    "04971": [
     "44.9330",
     "-69.3904"
    ]
   },
   "l": []
  },
  "stetson": {
   "z": {
    "04488": [
     "44.8770",
     "-69.1113"
    ]
   },
   "l": []
  },
  "litchfield": {
   "z": {
    "04350": [
     "44.1731",
     "-69.9377"
    ]
   },
   "l": []
  },
  "orland": {
   "z": {
    "04472": [
     "44.5598",
     "-68.6817"
    ]
   },
   "l": []
  },
  "durham": {
   "z": {
    "04222": [
     "43.9634",
     "-70.1311"
    ]
   },
   "l": []
  },
  "winterport": {
   "z": {
    "04496": [
     "44.6590",
     "-68.9200"
    ]
   },
   "l": []
  },
  "islesboro": {
   "z": {
    "04848": [
     "44.3121",
     "-68.9020"
    ]
   },
   "l": []
  },
  "east winthrop": {
   "z": {
    "04343": [
     "44.3217",
     "-69.8964"
    ]
   },
   "l": []
  },
  "washington": {
   "z": {
    "04574": [
     "44.2742",
     "-69.3875"
    ]
   },
   "l": []
  },
  "coopers mills": {
   "z": {
    "04341": [
     "44.2588",
     "-69.5510"
    ]
   },
   "l": []
  },
  "south gardiner": {
   "z": {
    "04359": [
     "44.1801",
     "-69.7567"
    ]
   },
   "l": []
  },
  "turner": {
   "z": {
    "04282": [
     "44.2718",
     "-70.2506"
    ]
   },
   "l": []
  },
  "franklin": {
   "z": {
    "04634": [
     "44.6466",
     "-68.0514"
    ]
   },
   "l": []
  },
  "holden": {
   "z": {
    "04429": [
     "44.7262",
     "-68.5995"
    ]
   },
   "l": []
  },
  "south china": {
   "z": {
    "04358": [
     "44.4195",
     "-69.4961"
    ]
   },
   "l": []
  },
  "danville": {
   "z": {
    "04223": [
     "44.0239",
     "-70.2857"
    ]
   },
   "l": []
  },
  "union": {
   "z": {
    "04862": [
     "44.2660",
     "-69.2796"
    ]
   },
   "l": []
  },
  "detroit": {
   "z": {
    "04929": [
     "44.7613",
     "-69.3165"
    ]
   },
   "l": []
  },
  "northeast harbor": {
   "z": {
    "04662": [
     "44.2942",
     "-68.2897"
    ]
   },
   "l": []
  },
  "orient": {
   "z": {
    "04471": [
     "45.9052",
     "-67.8780"
    ]
   },
   "l": []
  },
  "cape porpoise": {
   "z": {
    "04014": [
     "43.3726",
     "-70.4381"
    ]
   },
   "l": []
  },
  "east millinocket": {
   "z": {
    "04430": [
     "45.6739",
     "-68.5912"
    ]
   },
   "l": []
  },
  "norridgewock": {
   "z": {
    "04957": [
     "44.6879",
     "-69.8501"
    ]
   },
   "l": []
  },
  "north waterboro": {
   "z": {
    "04061": [
     "43.6328",
     "-70.7450"
    ]
   },
   "l": []
  },
  "surry": {
   "z": {
    "04684": [
     "44.4666",
     "-68.5285"
    ]
   },
   "l": []
  },
  "liberty": {
   "z": {
    "04949": [
     "44.3688",
     "-69.3317"
    ]
   },
   "l": []
  },
  "new sharon": {
   "z": {
    "04955": [
     "44.6447",
     "-70.0074"
    ]
   },
   "l": []
  },
  "dennysville": {
   "z": {
    "04628": [
     "44.9005",
     "-67.2717"
    ]
   },
   "l": []
  },
  "north yarmouth": {
   "z": {
    "04097": [
     "43.8352",
     "-70.2524"
    ]
   },
   "l": []
  },
  "york beach": {
   "z": {
    "03910": [
     "43.1715",
     "-70.6089"
    ],
    "03911": [
     "43.1715",
     "-70.6089"
    ]
   },
   "l": []
  },
  "cumberland center": {
   "z": {
    "04021": [
     "43.7977",
     "-70.2658"
    ]
   },
   "l": []
  },
  "raymond": {
   "z": {
    "04071": [
     "43.9276",
     "-70.4521"
    ]
   },
   "l": []
  },
  "pownal": {
   "z": {
    "04069": [
     "43.8945",
     "-70.1833"
    ]
   },
   "l": []
  },
  "bailey island": {
   "z": {
    "04003": [
     "43.7413",
     "-69.9926"
    ]
   },
   "l": []
  },
  "limerick": {
   "z": {
    "04048": [
     "43.6948",
     "-70.7941"
    ]
   },
   "l": []
  },
  "cape neddick": {
   "z": {
    "03902": [
     "43.2233",
     "-70.6420"
    ]
   },
   "l": []
  },
  "sebago": {
   "z": {
    "04029": [
     "43.8978",
     "-70.6901"
    ]
   },
   "l": []
  },
  "greenwood": {
   "z": {
    "04255": [
     "44.3382",
     "-70.6673"
    ]
   },
   "l": []
  },
  "east waterboro": {
   "z": {
    "04030": [
     "43.5835",
     "-70.7074"
    ]
   },
   "l": []
  },
  "hudson": {
   "z": {
    "04449": [
     "45.0041",
     "-68.8881"
    ]
   },
   "l": []
  },
  "frenchville": {
   "z": {
    "04745": [
     "47.2798",
     "-68.3923"
    ]
   },
   "l": []
  },
  "boothbay harbor": {
   "z": {
    "04538": [
     "43.8501",
     "-69.6325"
    ]
   },
   "l": []
  },
  "woolwich": {
   "z": {
    "04579": [
     "43.9565",
     "-69.7653"
    ]
   },
   "l": []
  },
  "fryeburg": {
   "z": {
    "04037": [
     "44.1003",
     "-70.9266"
    ]
   },
   "l": []
  },
  "buxton": {
   "z": {
    "04093": [
     "43.6606",
     "-70.5321"
    ]
   },
   "l": []
  },
  "hollis center": {
   "z": {
    "04042": [
     "43.6305",
     "-70.6181"
    ]
   },
   "l": []
  },
  "north monmouth": {
   "z": {
    "04265": [
     "44.2810",
     "-70.0332"
    ]
   },
   "l": []
  },
  "readfield": {
   "z": {
    "04355": [
     "44.3829",
     "-69.9501"
    ]
   },
   "l": []
  },
  "freedom": {
   "z": {
    "04941": [
     "44.4540",
     "-69.2997"
    ]
   },
   "l": []
  },
  "west paris": {
   "z": {
    "04289": [
     "44.3230",
     "-70.5790"
    ]
   },
   "l": []
  },
  "norway": {
   "z": {
    "04268": [
     "44.2245",
     "-70.6087"
    ]
   },
   "l": []
  },
  "south freeport": {
   "z": {
    "04078": [
     "43.8198",
     "-70.1095"
    ]
   },
   "l": []
  },
  "sebago lake": {
   "z": {
    "04075": [
     "43.7961",
     "-70.5522"
    ]
   },
   "l": []
  },
  "troy": {
   "z": {
    "04987": [
     "44.6784",
     "-69.2590"
    ]
   },
   "l": []
  },
  "china village": {
   "z": {
    "04926": [
     "44.4761",
     "-69.5164"
    ]
   },
   "l": []
  },
  "sabattus": {
   "z": {
    "04280": [
     "44.1316",
     "-70.0606"
    ]
   },
   "l": []
  },
  "south casco": {
   "z": {
    "04077": [
     "43.9148",
     "-70.5178"
    ]
   },
   "l": []
  },
  "newry": {
   "z": {
    "04261": [
     "44.5680",
     "-70.8697"
    ]
   },
   "l": []
  },
  "thomaston": {
   "z": {
    "04861": [
     "44.0964",
     "-69.1737"
    ]
   },
   "l": []
  },
  "palermo": {
   "z": {
    "04354": [
     "44.3960",
     "-69.4244"
    ]
   },
   "l": []
  },
  "mechanic falls": {
   "z": {
    "04256": [
     "44.1075",
     "-70.4051"
    ]
   },
   "l": []
  },
  "harrison": {
   "z": {
    "04040": [
     "44.0919",
     "-70.6434"
    ]
   },
   "l": []
  },
  "bradford": {
   "z": {
    "04410": [
     "45.0892",
     "-68.9071"
    ]
   },
   "l": []
  },
  "lincolnville": {
   "z": {
    "04849": [
     "44.3219",
     "-69.0596"
    ]
   },
   "l": []
  },
  "hiram": {
   "z": {
    "04041": [
     "43.8573",
     "-70.8384"
    ]
   },
   "l": []
  },
  "frankfort": {
   "z": {
    "04438": [
     "44.5997",
     "-68.9245"
    ]
   },
   "l": []
  },
  "lincolnville center": {
   "z": {
    "04850": [
     "44.2978",
     "-69.1075"
    ]
   },
   "l": []
  },
  "morrill": {
   "z": {
    "04952": [
     "44.4064",
     "-69.1377"
    ]
   },
   "l": []
  },
  "round pond": {
   "z": {
    "04564": [
     "43.9362",
     "-69.4734"
    ]
   },
   "l": []
  },
  "addison": {
   "z": {
    "04606": [
     "44.5703",
     "-67.6961"
    ]
   },
   "l": []
  },
  "thorndike": {
   "z": {
    "04986": [
     "44.5678",
     "-69.2190"
    ]
   },
   "l": []
  },
  "south windham": {
   "z": {
    "04082": [
     "43.7362",
     "-70.4237"
    ]
   },
   "l": []
  },
  "bowdoin": {
   "z": {
    "04287": [
     "44.0580",
     "-69.9676"
    ]
   },
   "l": []
  },
  "ogunquit": {
   "z": {
    "03907": [
     "43.2503",
     "-70.6033"
    ]
   },
   "l": []
  },
  "whitefield": {
   "z": {
    "04353": [
     "44.2007",
     "-69.6029"
    ]
   },
   "l": []
  },
  "dresden": {
   "z": {
    "04342": [
     "44.0720",
     "-69.7241"
    ]
   },
   "l": []
  },
  "belgrade lakes": {
   "z": {
    "04918": [
     "44.5216",
     "-69.8680"
    ]
   },
   "l": []
  },
  "wesley": {
   "z": {
    "04686": [
     "44.9870",
     "-67.7053"
    ]
   },
   "l": []
  },
  "east vassalboro": {
   "z": {
    "04935": [
     "44.4479",
     "-69.6059"
    ]
   },
   "l": []
  },
  "dixmont": {
   "z": {
    "04932": [
     "44.6949",
     "-69.1331"
    ]
   },
   "l": []
  },
  "east baldwin": {
   "z": {
    "04024": [
     "43.8295",
     "-70.6821"
    ]
   },
   "l": []
  },
  "hancock": {
   "z": {
    "04640": [
     "44.5274",
     "-68.2517"
    ]
   },
   "l": []
  },
  "randolph": {
   "z": {
    "04346": [
     "44.2352",
     "-69.7466"
    ]
   },
   "l": []
  },
  "island falls": {
   "z": {
    "04747": [
     "46.0013",
     "-68.2222"
    ]
   },
   "l": []
  },
  "westfield": {
   "z": {
    "04787": [
     "46.5520",
     "-67.9770"
    ]
   },
   "l": []
  },
  "mapleton": {
   "z": {
    "04757": [
     "46.6095",
     "-68.1755"
    ]
   },
   "l": []
  },
  "waite": {
   "z": {
    "04492": [
     "45.3548",
     "-67.6520"
    ]
   },
   "l": []
  },
  "perry": {
   "z": {
    "04667": [
     "44.9867",
     "-67.1114"
    ]
   },
   "l": []
  },
  "lubec": {
   "z": {
    "04652": [
     "44.8081",
     "-67.0592"
    ]
   },
   "l": []
  },
  "shapleigh": {
   "z": {
    "04076": [
     "43.5489",
     "-70.8444"
    ]
   },
   "l": []
  },
  "whiting": {
   "z": {
    "04691": [
     "44.8523",
     "-67.3506"
    ]
   },
   "l": []
  },
  "shawmut": {
   "z": {
    "04975": [
     "44.6278",
     "-69.5864"
    ]
   },
   "l": []
  },
  "limington": {
   "z": {
    "04049": [
     "43.7306",
     "-70.7054"
    ]
   },
   "l": []
  },
  "medway": {
   "z": {
    "04460": [
     "45.7052",
     "-68.4838"
    ]
   },
   "l": []
  },
  "north turner": {
   "z": {
    "04266": [
     "44.3580",
     "-70.2558"
    ]
   },
   "l": []
  },
  "bryant pond": {
   "z": {
    "04219": [
     "44.4120",
     "-70.5999"
    ]
   },
   "l": []
  },
  "paris": {
   "z": {
    "04271": [
     "44.2598",
     "-70.5006"
    ]
   },
   "l": []
  },
  "levant": {
   "z": {
    "04456": [
     "44.8895",
     "-68.9877"
    ]
   },
   "l": []
  },
  "wallagrass": {
   "z": {
    "04781": [
     "47.1482",
     "-68.6224"
    ]
   },
   "l": []
  },
  "howland": {
   "z": {
    "04448": [
     "45.3257",
     "-68.7142"
    ]
   },
   "l": []
  },
  "lagrange": {
   "z": {
    "04453": [
     "45.1919",
     "-68.7780"
    ]
   },
   "l": []
  },
  "olamon": {
   "z": {
    "04467": [
     "45.1209",
     "-68.6106"
    ]
   },
   "l": []
  },
  "kenduskeag": {
   "z": {
    "04450": [
     "44.9169",
     "-68.9288"
    ]
   },
   "l": []
  },
  "hope": {
   "z": {
    "04847": [
     "44.2519",
     "-69.1883"
    ]
   },
   "l": []
  },
  "saint francis": {
   "z": {
    "04774": [
     "47.1122",
     "-69.0569"
    ]
   },
   "l": []
  },
  "sherman": {
   "z": {
    "04776": [
     "45.8445",
     "-68.3179"
    ]
   },
   "l": []
  },
  "ocean park": {
   "z": {
    "04063": [
     "43.5006",
     "-70.3862"
    ]
   },
   "l": []
  },
  "brownville": {
   "z": {
    "04414": [
     "45.4353",
     "-69.0801"
    ]
   },
   "l": []
  },
  "east poland": {
   "z": {
    "04230": [
     "44.0706",
     "-70.3281"
    ]
   },
   "l": []
  },
  "smithfield": {
   "z": {
    "04978": [
     "44.6280",
     "-69.8065"
    ]
   },
   "l": []
  },
  "bustins island": {
   "z": {
    "04013": [
     "44.4081",
     "-70.4707"
    ]
   },
   "l": []
  },
  "west boothbay harbor": {
   "z": {
    "04575": [
     "43.8490",
     "-69.6434"
    ]
   },
   "l": []
  },
  "cornish": {
   "z": {
    "04020": [
     "43.7616",
     "-70.8079"
    ]
   },
   "l": []
  },
  "anson": {
   "z": {
    "04911": [
     "44.7725",
     "-69.9588"
    ]
   },
   "l": []
  },
  "new vineyard": {
   "z": {
    "04956": [
     "44.7995",
     "-70.1054"
    ]
   },
   "l": []
  },
  "corinna": {
   "z": {
    "04928": [
     "44.9508",
     "-69.2572"
    ]
   },
   "l": []
  },
  "swans island": {
   "z": {
    "04685": [
     "44.1596",
     "-68.4437"
    ]
   },
   "l": []
  },
  "strong": {
   "z": {
    "04983": [
     "44.8963",
     "-70.3263"
    ]
   },
   "l": []
  },
  "canaan": {
   "z": {
    "04924": [
     "44.7820",
     "-69.5421"
    ]
   },
   "l": []
  },
  "bass harbor": {
   "z": {
    "04653": [
     "44.1899",
     "-68.3647"
    ]
   },
   "l": []
  },
  "north vassalboro": {
   "z": {
    "04962": [
     "44.4770",
     "-69.6140"
    ]
   },
   "l": []
  },
  "temple": {
   "z": {
    "04984": [
     "44.6975",
     "-70.2755"
    ]
   },
   "l": []
  },
  "weld": {
   "z": {
    "04285": [
     "44.7070",
     "-70.4530"
    ]
   },
   "l": []
  },
  "sebec": {
   "z": {
    "04481": [
     "45.2605",
     "-69.1202"
    ]
   },
   "l": []
  },
  "brownfield": {
   "z": {
    "04010": [
     "43.9347",
     "-70.9086"
    ]
   },
   "l": []
  },
  "leeds": {
   "z": {
    "04263": [
     "44.2888",
     "-70.1353"
    ]
   },
   "l": []
  },
  "monroe": {
   "z": {
    "04951": [
     "44.6067",
     "-69.0370"
    ]
   },
   "l": []
  },
  "orrington": {
   "z": {
    "04474": [
     "44.7135",
     "-68.7799"
    ]
   },
   "l": []
  },
  "east orland": {
   "z": {
    "04431": [
     "44.5784",
     "-68.6728"
    ]
   },
   "l": []
  },
  "salsbury cove": {
   "z": {
    "04672": [
     "44.4306",
     "-68.2836"
    ]
   },
   "l": []
  },
  "livermore": {
   "z": {
    "04253": [
     "44.4047",
     "-70.2151"
    ]
   },
   "l": []
  },
  "livermore falls": {
   "z": {
    "04254": [
     "44.4285",
     "-70.1499"
    ]
   },
   "l": []
  },
  "searsmont": {
   "z": {
    "04973": [
     "44.3668",
     "-69.1889"
    ]
   },
   "l": []
  },
  "sumner": {
   "z": {
    "04292": [
     "44.3765",
     "-70.4361"
    ]
   },
   "l": []
  },
  "canton": {
   "z": {
    "04221": [
     "44.4139",
     "-70.3304"
    ]
   },
   "l": []
  },
  "hebron": {
   "z": {
    "04238": [
     "44.1945",
     "-70.3778"
    ]
   },
   "l": []
  },
  "wayne": {
   "z": {
    "04284": [
     "44.3405",
     "-70.0721"
    ]
   },
   "l": []
  },
  "monmouth": {
   "z": {
    "04259": [
     "44.2257",
     "-70.0062"
    ]
   },
   "l": []
  },
  "southwest harbor": {
   "z": {
    "04679": [
     "44.2735",
     "-68.3373"
    ]
   },
   "l": []
  },
  "minot": {
   "z": {
    "04258": [
     "44.1462",
     "-70.3439"
    ]
   },
   "l": []
  },
  "walpole": {
   "z": {
    "04573": [
     "43.9502",
     "-69.5567"
    ]
   },
   "l": []
  },
  "stockholm": {
   "z": {
    "04783": [
     "47.0424",
     "-68.2121"
    ]
   },
   "l": []
  },
  "milford": {
   "z": {
    "04461": [
     "44.9719",
     "-68.5243"
    ]
   },
   "l": []
  },
  "blaine": {
   "z": {
    "04734": [
     "46.4763",
     "-67.8550"
    ]
   },
   "l": []
  },
  "smyrna mills": {
   "z": {
    "04780": [
     "46.1875",
     "-68.2028"
    ]
   },
   "l": []
  },
  "peru": {
   "z": {
    "04290": [
     "44.4758",
     "-70.4554"
    ]
   },
   "l": []
  },
  "roxbury": {
   "z": {
    "04275": [
     "44.6934",
     "-70.6399"
    ]
   },
   "l": []
  },
  "little deer isle": {
   "z": {
    "04650": [
     "44.2899",
     "-68.7079"
    ]
   },
   "l": []
  },
  "east blue hill": {
   "z": {
    "04629": [
     "44.4176",
     "-68.5225"
    ]
   },
   "l": []
  },
  "west baldwin": {
   "z": {
    "04091": [
     "43.8315",
     "-70.7547"
    ]
   },
   "l": []
  },
  "east livermore": {
   "z": {
    "04228": [
     "44.4010",
     "-70.1338"
    ]
   },
   "l": []
  },
  "portage": {
   "z": {
    "04768": [
     "46.7842",
     "-68.5074"
    ]
   },
   "l": []
  },
  "washburn": {
   "z": {
    "04786": [
     "46.7802",
     "-68.1779"
    ]
   },
   "l": []
  },
  "bar mills": {
   "z": {
    "04004": [
     "43.6131",
     "-70.5498"
    ]
   },
   "l": []
  },
  "saint agatha": {
   "z": {
    "04772": [
     "47.2225",
     "-68.2871"
    ]
   },
   "l": []
  },
  "lovell": {
   "z": {
    "04051": [
     "44.1883",
     "-70.8812"
    ]
   },
   "l": []
  },
  "corinth": {
   "z": {
    "04427": [
     "44.9821",
     "-69.0133"
    ]
   },
   "l": []
  },
  "glen cove": {
   "z": {
    "04846": [
     "44.1337",
     "-69.0942"
    ]
   },
   "l": []
  },
  "waterford": {
   "z": {
    "04088": [
     "44.2012",
     "-70.7174"
    ]
   },
   "l": []
  },
  "moody": {
   "z": {
    "04054": [
     "44.9803",
     "-69.3000"
    ]
   },
   "l": []
  },
  "brooks": {
   "z": {
    "04921": [
     "44.5655",
     "-69.1275"
    ]
   },
   "l": []
  },
  "grand lake stream": {
   "z": {
    "04637": [
     "45.1795",
     "-67.7745"
    ]
   },
   "l": []
  },
  "plymouth": {
   "z": {
    "04969": [
     "44.7716",
     "-69.2171"
    ]
   },
   "l": []
  },
  "hinckley": {
   "z": {
    "04944": [
     "44.6856",
     "-69.6325"
    ]
   },
   "l": []
  },
  "bradley": {
   "z": {
    "04411": [
     "44.8804",
     "-68.5718"
    ]
   },
   "l": []
  },
  "passadumkeag": {
   "z": {
    "04475": [
     "45.2024",
     "-68.5953"
    ]
   },
   "l": []
  },
  "west poland": {
   "z": {
    "04291": [
     "44.0409",
     "-70.4530"
    ]
   },
   "l": []
  },
  "meddybemps": {
   "z": {
    "04657": [
     "44.9688",
     "-67.4054"
    ]
   },
   "l": []
  },
  "danforth": {
   "z": {
    "04424": [
     "45.6774",
     "-67.8229"
    ]
   },
   "l": []
  },
  "hanover": {
   "z": {
    "04237": [
     "44.4953",
     "-70.7374"
    ]
   },
   "l": []
  },
  "port clyde": {
   "z": {
    "04855": [
     "43.9273",
     "-69.2528"
    ]
   },
   "l": []
  },
  "crouseville": {
   "z": {
    "04738": [
     "46.7550",
     "-68.0964"
    ]
   },
   "l": []
  },
  "cliff island": {
   "z": {
    "04019": [
     "43.6968",
     "-70.0911"
    ]
   },
   "l": []
  },
  "east dixfield": {
   "z": {
    "04227": [
     "44.5734",
     "-70.3037"
    ]
   },
   "l": []
  },
  "frenchboro": {
   "z": {
    "04635": [
     "44.1129",
     "-68.3536"
    ]
   },
   "l": []
  },
  "bridgewater": {
   "z": {
    "04735": [
     "46.4255",
     "-67.9778"
    ]
   },
   "l": []
  },
  "springfield": {
   "z": {
    "04487": [
     "45.4386",
     "-68.1316"
    ]
   },
   "l": []
  },
  "center lovell": {
   "z": {
    "04016": [
     "44.1785",
     "-70.8984"
    ]
   },
   "l": []
  },
  "eustis": {
   "z": {
    "04936": [
     "45.3972",
     "-70.6269"
    ]
   },
   "l": []
  },
  "eastport": {
   "z": {
    "04631": [
     "44.9207",
     "-67.0155"
    ]
   },
   "l": []
  },
  "new limerick": {
   "z": {
    "04761": [
     "46.1180",
     "-67.9721"
    ]
   },
   "l": []
  },
  "abbot": {
   "z": {
    "04406": [
     "45.2275",
     "-69.5548"
    ]
   },
   "l": []
  },
  "acton": {
   "z": {
    "04001": [
     "43.5350",
     "-70.9169"
    ]
   },
   "l": []
  },
  "rangeley": {
   "z": {
    "04970": [
     "44.9816",
     "-70.6514"
    ]
   },
   "l": []
  },
  "friendship": {
   "z": {
    "04547": [
     "44.0119",
     "-69.3231"
    ]
   },
   "l": []
  },
  "monticello": {
   "z": {
    "04760": [
     "46.3215",
     "-67.8455"
    ]
   },
   "l": []
  },
  "york harbor": {
   "z": {
    "03911": [
     "43.1368",
     "-70.6456"
    ]
   },
   "l": []
  },
  "pembroke": {
   "z": {
    "04666": [
     "44.9769",
     "-67.2324"
    ]
   },
   "l": []
  },
  "west enfield": {
   "z": {
    "04493": [
     "45.2426",
     "-68.5468"
    ]
   },
   "l": []
  },
  "cambridge": {
   "z": {
    "04923": [
     "45.0341",
     "-69.4369"
    ]
   },
   "l": []
  },
  "north haven": {
   "z": {
    "04853": [
     "44.1480",
     "-68.8758"
    ]
   },
   "l": []
  },
  "new sweden": {
   "z": {
    "04762": [
     "46.9743",
     "-68.1449"
    ]
   },
   "l": []
  },
  "harpswell": {
   "z": {
    "04079": [
     "43.8122",
     "-69.8888"
    ]
   },
   "l": []
  },
  "sandy point": {
   "z": {
    "04972": [
     "44.5148",
     "-68.8128"
    ]
   },
   "l": []
  },
  "burlington": {
   "z": {
    "04417": [
     "45.2339",
     "-68.3757"
    ]
   },
   "l": []
  },
  "dryden": {
   "z": {
    "04225": [
     "44.5721",
     "-70.1870"
    ]
   },
   "l": []
  },
  "farmington falls": {
   "z": {
    "04940": [
     "44.6209",
     "-70.0753"
    ]
   },
   "l": []
  },
  "vienna": {
   "z": {
    "04360": [
     "44.5460",
     "-70.0024"
    ]
   },
   "l": []
  },
  "cushing": {
   "z": {
    "04563": [
     "44.0094",
     "-69.2521"
    ]
   },
   "l": []
  },
  "long island": {
   "z": {
    "04050": [
     "43.6915",
     "-70.1537"
    ]
   },
   "l": []
  },
  "andover": {
   "z": {
    "04216": [
     "44.6600",
     "-70.8084"
    ]
   },
   "l": []
  },
  "saint david": {
   "z": {
    "04773": [
     "47.2545",
     "-68.2249"
    ]
   },
   "l": []
  },
  "sinclair": {
   "z": {
    "04779": [
     "47.1430",
     "-68.2678"
    ]
   },
   "l": []
  },
  "seal cove": {
   "z": {
    "04674": [
     "44.3006",
     "-68.3883"
    ]
   },
   "l": []
  },
  "east boothbay": {
   "z": {
    "04544": [
     "43.8433",
     "-69.5894"
    ]
   },
   "l": []
  },
  "east newport": {
   "z": {
    "04933": [
     "44.8209",
     "-69.2225"
    ]
   },
   "l": []
  },
  "robbinston": {
   "z": {
    "04671": [
     "45.0622",
     "-67.1741"
    ]
   },
   "l": []
  },
  "dixfield": {
   "z": {
    "04224": [
     "44.5801",
     "-70.4154"
    ]
   },
   "l": []
  },
  "sullivan": {
   "z": {
    "04664": [
     "44.5404",
     "-68.2186"
    ]
   },
   "l": []
  },
  "shirley mills": {
   "z": {
    "04485": [
     "45.3656",
     "-69.6181"
    ]
   },
   "l": []
  },
  "stacyville": {
   "z": {
    "04777": [
     "45.8564",
     "-68.4832"
    ]
   },
   "l": []
  },
  "patten": {
   "z": {
    "04765": [
     "46.1616",
     "-68.5836"
    ]
   },
   "l": []
  },
  "benedicta": {
   "z": {
    "04733": [
     "45.7408",
     "-68.3619"
    ]
   },
   "l": []
  },
  "wytopitlock": {
   "z": {
    "04497": [
     "45.7913",
     "-68.1037"
    ]
   },
   "l": []
  },
  "west farmington": {
   "z": {
    "04992": [
     "44.6628",
     "-70.1553"
    ]
   },
   "l": []
  },
  "harrington": {
   "z": {
    "04643": [
     "44.5763",
     "-67.7706"
    ]
   },
   "l": []
  },
  "bristol": {
   "z": {
    "04539": [
     "43.9569",
     "-69.5028"
    ]
   },
   "l": []
  },
  "easton": {
   "z": {
    "04740": [
     "46.6567",
     "-67.8552"
    ]
   },
   "l": []
  },
  "stoneham": {
   "z": {
    "04231": [
     "44.2606",
     "-70.8819"
    ]
   },
   "l": []
  },
  "north anson": {
   "z": {
    "04958": [
     "44.8939",
     "-69.9374"
    ]
   },
   "l": []
  },
  "owls head": {
   "z": {
    "04854": [
     "44.0650",
     "-69.0884"
    ]
   },
   "l": []
  },
  "sorrento": {
   "z": {
    "04677": [
     "44.4919",
     "-68.1780"
    ]
   },
   "l": []
  },
  "isle au haut": {
   "z": {
    "04645": [
     "44.0480",
     "-68.6302"
    ]
   },
   "l": []
  },
  "spruce head": {
   "z": {
    "04859": [
     "44.0058",
     "-69.1646"
    ]
   },
   "l": []
  },
  "bremen": {
   "z": {
    "04551": [
     "44.0154",
     "-69.4403"
    ]
   },
   "l": []
  },
  "biddeford pool": {
   "z": {
    "04006": [
     "43.4455",
     "-70.3436"
    ]
   },
   "l": []
  },
  "porter": {
   "z": {
    "04068": [
     "43.8372",
     "-70.9364"
    ]
   },
   "l": []
  },
  "athens": {
   "z": {
    "04912": [
     "44.9878",
     "-69.6738"
    ]
   },
   "l": []
  },
  "orrs island": {
   "z": {
    "04066": [
     "43.7727",
     "-69.9670"
    ]
   },
   "l": []
  },
  "tenants harbor": {
   "z": {
    "04860": [
     "43.9750",
     "-69.2308"
    ]
   },
   "l": []
  },
  "rockwood": {
   "z": {
    "04478": [
     "45.7713",
     "-69.8381"
    ]
   },
   "l": []
  },
  "south thomaston": {
   "z": {
    "04858": [
     "44.0445",
     "-69.1465"
    ]
   },
   "l": []
  },
  "north jay": {
   "z": {
    "04262": [
     "44.5473",
     "-70.2381"
    ]
   },
   "l": []
  },
  "oquossoc": {
   "z": {
    "04964": [
     "44.9664",
     "-70.7737"
    ]
   },
   "l": []
  },
  "harmony": {
   "z": {
    "04942": [
     "45.0601",
     "-69.5873"
    ]
   },
   "l": []
  },
  "east andover": {
   "z": {
    "04226": [
     "44.6124",
     "-70.6987"
    ]
   },
   "l": []
  },
  "lee": {
   "z": {
    "04455": [
     "45.3236",
     "-68.2742"
    ]
   },
   "l": []
  },
  "garland": {
   "z": {
    "04939": [
     "45.0560",
     "-69.1499"
    ]
   },
   "l": []
  },
  "north waterford": {
   "z": {
    "04267": [
     "44.2098",
     "-70.8133"
    ]
   },
   "l": []
  },
  "alna": {
   "z": {
    "04535": [
     "44.0845",
     "-69.6278"
    ]
   },
   "l": []
  },
  "oakfield": {
   "z": {
    "04763": [
     "46.1187",
     "-68.1118"
    ]
   },
   "l": []
  },
  "stonington": {
   "z": {
    "04681": [
     "44.1683",
     "-68.6648"
    ]
   },
   "l": []
  },
  "bernard": {
   "z": {
    "04612": [
     "44.2548",
     "-68.3752"
    ]
   },
   "l": []
  },
  "gouldsboro": {
   "z": {
    "04607": [
     "44.5093",
     "-68.0899"
    ]
   },
   "l": []
  },
  "stratton": {
   "z": {
    "04982": [
     "45.1022",
     "-70.4410"
    ]
   },
   "l": []
  },
  "steuben": {
   "z": {
    "04680": [
     "44.4959",
     "-67.9476"
    ]
   },
   "l": []
  },
  "van buren": {
   "z": {
    "04785": [
     "47.1538",
     "-67.9568"
    ]
   },
   "l": []
  },
  "princeton": {
   "z": {
    "04668": [
     "45.1844",
     "-67.6204"
    ]
   },
   "l": []
  },
  "mattawamkeag": {
   "z": {
    "04459": [
     "45.5920",
     "-68.3160"
    ]
   },
   "l": []
  },
  "monhegan": {
   "z": {
    "04852": [
     "43.7653",
     "-69.3120"
    ]
   },
   "l": []
  },
  "pemaquid": {
   "z": {
    "04558": [
     "43.9033",
     "-69.5088"
    ]
   },
   "l": []
  },
  "chamberlain": {
   "z": {
    "04541": [
     "43.8862",
     "-69.4743"
    ]
   },
   "l": []
  },
  "new harbor": {
   "z": {
    "04554": [
     "43.8576",
     "-69.5051"
    ]
   },
   "l": []
  },
  "matinicus": {
   "z": {
    "04851": [
     "43.8621",
     "-68.8951"
    ]
   },
   "l": []
  },
  "newfield": {
   "z": {
    "04056": [
     "43.6481",
     "-70.8470"
    ]
   },
   "l": []
  },
  "cutler": {
   "z": {
    "04626": [
     "44.6875",
     "-67.2232"
    ]
   },
   "l": []
  },
  "caratunk": {
   "z": {
    "04925": [
     "45.2154",
     "-69.9042"
    ]
   },
   "l": []
  },
  "bingham": {
   "z": {
    "04920": [
     "45.1053",
     "-69.8444"
    ]
   },
   "l": []
  },
  "corea": {
   "z": {
    "04624": [
     "44.4198",
     "-67.9853"
    ]
   },
   "l": []
  },
  "kingman": {
   "z": {
    "04451": [
     "45.6241",
     "-68.2068"
    ]
   },
   "l": []
  },
  "south bristol": {
   "z": {
    "04568": [
     "43.8941",
     "-69.5633"
    ]
   },
   "l": []
  },
  "trevett": {
   "z": {
    "04571": [
     "43.9016",
     "-69.6759"
    ]
   },
   "l": []
  },
  "sebasco estates": {
   "z": {
    "04565": [
     "43.7733",
     "-69.8635"
    ]
   },
   "l": []
  },
  "west minot": {
   "z": {
    "04288": [
     "44.1712",
     "-70.3659"
    ]
   },
   "l": []
  },
  "hulls cove": {
   "z": {
    "04644": [
     "44.4192",
     "-68.2506"
    ]
   },
   "l": []
  },
  "greenville junction": {
   "z": {
    "04442": [
     "45.4856",
     "-69.6909"
    ]
   },
   "l": []
  },
  "west bethel": {
   "z": {
    "04286": [
     "44.4020",
     "-70.8612"
    ]
   },
   "l": []
  },
  "fort kent mills": {
   "z": {
    "04744": [
     "47.2389",
     "-68.5839"
    ]
   },
   "l": []
  },
  "jackman": {
   "z": {
    "04945": [
     "45.5608",
     "-70.2599"
    ]
   },
   "l": []
  },
  "islesford": {
   "z": {
    "04646": [
     "44.2591",
     "-68.2262"
    ]
   },
   "l": []
  },
  "winn": {
   "z": {
    "04495": [
     "45.4535",
     "-68.3543"
    ]
   },
   "l": []
  },
  "brownville junction": {
   "z": {
    "04415": [
     "45.3501",
     "-69.0523"
    ]
   },
   "l": []
  },
  "west forks": {
   "z": {
    "04985": [
     "45.3649",
     "-69.8989"
    ]
   },
   "l": []
  },
  "sargentville": {
   "z": {
    "04673": [
     "44.3168",
     "-68.6747"
    ]
   },
   "l": []
  },
  "grand isle": {
   "z": {
    "04746": [
     "47.2661",
     "-68.1303"
    ]
   },
   "l": []
  },
  "beals": {
   "z": {
    "04611": [
     "44.4819",
     "-67.5846"
    ]
   },
   "l": []
  },
  "oxbow": {
   "z": {
    "04764": [
     "46.4269",
     "-68.4719"
    ]
   },
   "l": []
  },
  "brookton": {
   "z": {
    "04413": [
     "45.5992",
     "-67.7074"
    ]
   },
   "l": []
  },
  "monson": {
   "z": {
    "04464": [
     "45.3006",
     "-69.5092"
    ]
   },
   "l": []
  },
  "s central washington co": {
   "z": {
    "04694": [
     "45.1285",
     "-67.4510"
    ]
   },
   "l": []
  },
  "sherman mills": {
   "z": {
    "04776": [
     "45.8445",
     "-68.3179"
    ]
   },
   "l": []
  },
  "central aroostook cnty": {
   "z": {
    "04732": [
     "46.6077",
     "-68.4102"
    ]
   },
   "l": []
  },
  "northern washington co": {
   "z": {
    "04492": [
     "45.3548",
     "-67.6520"
    ]
   },
   "l": []
  },
  "sherman station": {
   "z": {
    "04777": [
     "45.8564",
     "-68.4832"
    ]
   },
   "l": []
  },
  "perham": {
   "z": {
    "04766": [
     "46.8817",
     "-68.2388"
    ]
   },
   "l": []
  },
  "east central franklin": {
   "z": {
    "04970": [
     "44.9816",
     "-70.6514"
    ]
   },
   "l": []
  },
  "sunset": {
   "z": {
    "04683": [
     "44.2103",
     "-68.7771"
    ]
   },
   "l": []
  },
  "cranberry isles": {
   "z": {
    "04625": [
     "44.2471",
     "-68.2412"
    ]
   },
   "l": []
  },
  "vanceboro": {
   "z": {
    "04491": [
     "45.4249",
     "-67.5107"
    ]
   },
   "l": []
  },
  "birch harbor": {
   "z": {
    "04613": [
     "44.3957",
     "-68.0372"
    ]
   },
   "l": []
  },
  "pride": {
   "z": {},
   "l": [
    "46.3506",
    "-68.2725"
   ]
  },
  "prairie": {
   "z": {},
   "l": [
    "45.4087",
    "-69.0639"
   ]
  },
  "newhall": {
   "z": {},
   "l": [
    "43.7515",
    "-70.4317"
   ]
  },
  "houghton": {
   "z": {},
   "l": [
    "44.7651",
    "-70.6495"
   ]
  },
  "reach": {
   "z": {},
   "l": [
    "44.2493",
    "-68.6236"
   ]
  },
  "china": {
   "z": {},
   "l": [
    "44.4787",
    "-69.5173"
   ]
  },
  "mariner": {
   "z": {},
   "l": [
    "43.6970",
    "-70.1509"
   ]
  },
  "blue hill falls": {
   "z": {
    "04615": [
     "44.3489",
     "-68.5058"
    ]
   },
   "l": []
  },
  "ketchum": {
   "z": {},
   "l": [
    "44.5028",
    "-70.9151"
   ]
  },
  "lambert lake": {
   "z": {
    "04454": [
     "45.5683",
     "-67.5532"
    ]
   },
   "l": []
  },
  "east parsonfield": {
   "z": {
    "04028": [
     "43.7653",
     "-70.9179"
    ]
   },
   "l": []
  },
  "isle of springs": {
   "z": {
    "04549": [
     "44.0213",
     "-69.5233"
    ]
   },
   "l": []
  },
  "squirrel island": {
   "z": {
    "04570": [
     "43.8070",
     "-69.6344"
    ]
   },
   "l": []
  }
 },
 "l": [
  "44.0845",
  "-70.1696"
 ]
}