{
 "c": {
  "princesa": {
   "z": {},
   "l": [
    "8.0205",
    "123.7915"
   ]
  },
  "cagayan": {
   "z": {},
   "l": [
    "7.9177",
    "123.6745"
   ]
  },
  "madaya": {
   "z": {},
   "l": [
    "7.8951",
    "123.8687"
   ]
  },
  "salvador": {
   "z": {},
   "l": [
    "7.9042",
    "123.8399"
   ]
  },
  "maigo": {
   "z": {},
   "l": [
    "8.1581",
    "123.9611"
   ]
  },
  "bunawan": {
   "z": {},
   "l": [
    "8.3167",
    "124.3031"
   ]
  },
  "digkilaan": {
   "z": {},
   "l": [
    "8.2511",
    "124.3172"
   ]
  },
  "kalanganan": {
   "z": {},
   "l": [
    "8.0836",
    "124.2481"
   ]
  },
  "tacub": {
   "z": {},
   "l": [
    "8.1853",
    "124.1194"
   ]
  },
  "kawit": {
   "z": {},
   "l": [
    "8.1875",
    "124.0667"
   ]
  },
  "kauswagan": {
   "z": {},
   "l": [
    "8.1892",
    "124.0894"
   ]
  },
  "lapinig": {
   "z": {},
   "l": [
    "7.9211",
    "123.6897"
   ]
  },
  "silang": {
   "z": {},
   "l": [
    "7.8839",
    "123.7983"
   ]
  },
  "tubod": {
   "z": {},
   "l": [
    "8.0555",
    "123.7904"
   ]
  },
  "baroy": {
   "z": {},
   "l": [
    "8.0269",
    "123.7784"
   ]
  },
  "pualas": {
   "z": {},
   "l": [
    "8.0172",
    "123.8481"
   ]
  },
  "kapatagan": {
   "z": {},
   "l": [
    "7.9003",
    "123.7692"
   ]
  },
  "lala": {
   "z": {},
   "l": [
    "7.9745",
    "123.7458"
   ]
  },
  "linamon": {
   "z": {},
   "l": [
    "8.1860",
    "124.1628"
   ]
  },
  "baloi": {
   "z": {},
   "l": [
    "8.1172",
    "124.2186"
   ]
  }
 },
 "l": []
}