{
 "c": {
  "pampanga": {
   "z": {
    "2005": [
     "7.1100",
     "125.6489"
    ],
    "2017": [
     "7.1100",
     "125.6489"
    ],
    "2022": [
     "7.1100",
     "125.6489"
    ]
   },
   "l": [
    "7.1100",
    "125.6489"
   ]
  },
  "davao": {
   "z": {
    "8112": [
     "7.0731",
     "125.6128"
    ]
   },
   "l": [
    "7.0731",
    "125.6128"
   ]
  },
  "lacson": {
   "z": {},
   "l": [
    "7.2119",
    "125.4422"
   ]
  },
  "manuel": {
   "z": {},
   "l": [
    "7.1486",
    "125.4989"
   ]
  },
  "ma-a": {
   "z": {},
   "l": [
    "7.0889",
    "125.5806"
   ]
  },
  "biao": {
   "z": {},
   "l": [
    "7.1633",
    "125.5211"
   ]
  },
  "tugbok": {
   "z": {},
   "l": [
    "7.1086",
    "125.4853"
   ]
  },
  "bato": {
   "z": {},
   "l": [
    "7.0431",
    "125.4731"
   ]
  },
  "lasang": {
   "z": {},
   "l": [
    "7.2669",
    "125.6650"
   ]
  },
  "tagakpan": {
   "z": {},
   "l": [
    "7.1128",
    "125.4292"
   ]
  },
  "mahayag": {
   "z": {},
   "l": [
    "7.2167",
    "125.6194"
   ]
  },
  "ventura": {
   "z": {},
   "l": [
    "7.2097",
    "125.3856"
   ]
  },
  "mintal": {
   "z": {},
   "l": [
    "7.0931",
    "125.5022"
   ]
  },
  "ilang": {
   "z": {},
   "l": [
    "7.1789",
    "125.6525"
   ]
  },
  "matina": {
   "z": {},
   "l": [
    "7.0447",
    "125.5681"
   ]
  },
  "calinan": {
   "z": {},
   "l": [
    "7.1872",
    "125.4544"
   ]
  },
  "lumot": {
   "z": {},
   "l": [
    "7.0581",
    "125.3647"
   ]
  },
  "davao city": {
   "z": {},
   "l": [
    "7.0731",
    "125.6128"
   ]
  }
 },
 "l": [
  "7.0731",
  "125.6128"
 ]
}