{
 "c": {
  "lopez": {
   "z": {},
   "l": [
    "10.5333",
    "123.4167"
   ]
  },
  "rigor": {
   "z": {},
   "l": [
    "10.4833",
    "123.4167"
   ]
  },
  "san carlos": {
   "z": {},
   "l": [
    "10.4840",
    "123.4203"
   ]
  },
  "palampas": {
   "z": {},
   "l": [
    "10.5278",
    "123.4047"
   ]
  },
  "codcod": {
   "z": {},
   "l": [
    "10.4581",
    "123.2222"
   ]
  },
  "igmaya-an": {
   "z": {},
   "l": [
    "10.5506",
    "123.2364"
   ]
  },
  "prosperidad": {
   "z": {},
   "l": [
    "10.5161",
    "123.3064"
   ]
  },
  "guadalupe": {
   "z": {},
   "l": [
    "10.4558",
    "123.3731"
   ]
  },
  "buluangan": {
   "z": {},
   "l": [
    "10.3919",
    "123.3392"
   ]
  },
  "kumaliskis": {
   "z": {},
   "l": [
    "10.5075",
    "123.2033"
   ]
  },
  "fortuna": {
   "z": {},
   "l": [
    "10.4144",
    "123.3492"
   ]
  },
  "san carlos city": {
   "z": {},
   "l": [
    "10.4840",
    "123.4203"
   ]
  }
 },
 "l": []
}