{
 "c": {
  "dimitrovgrad": {
   "z": {
    "6400": [
     "42.0500",
     "25.6000"
    ]
   },
   "l": [
    "42.0500",
    "25.6000"
   ]
  },
  "svilengrad": {
   "z": {
    "6500": [
     "41.7667",
     "26.2000"
    ]
   },
   "l": [
    "41.7667",
    "26.2000"
   ]
  },
  "bulgarin": {
   "z": {},
   "l": [
    "41.9500",
    "25.9500"
   ]
  },
  "haskovo": {
   "z": {
    "6300": [
     "41.9403",
     "25.5694"
    ]
   },
   "l": [
    "41.9403",
    "25.5694"
   ]
  },
  "harmanli": {
   "z": {
    "6450": [
     "41.9333",
     "25.9000"
    ]
   },
   "l": [
    "41.9333",
    "25.9000"
   ]
  },
  "most": {
   "z": {},
   "l": [
    "41.7333",
    "25.5167"
   ]
  },
  "maritsa": {
   "z": {},
   "l": [
    "42.0333",
    "25.8333"
   ]
  },
  "ljubimetz": {
   "z": {},
   "l": [
    "41.8333",
    "26.0833"
   ]
  },
  "oriahovica": {
   "z": {},
   "l": [
    "42.4833",
    "25.8167"
   ]
  },
  "rodopi": {
   "z": {},
   "l": [
    "41.9167",
    "25.7667"
   ]
  },
  "musachevo": {
   "z": {},
   "l": [
    "42.1000",
    "25.8333"
   ]
  },
  "pepelishte": {
   "z": {},
   "l": [
    "41.5833",
    "25.3833"
   ]
  },
  "topolovgrad": {
   "z": {
    "6560": [
     "42.0833",
     "26.3333"
    ]
   },
   "l": [
    "42.0833",
    "26.3333"
   ]
  },
  "simeonovgrad": {
   "z": {
    "6490": [
     "42.0333",
     "25.8333"
    ]
   },
   "l": [
    "42.0333",
    "25.8333"
   ]
  },
  "mericleri": {
   "z": {},
   "l": [
    "42.1333",
    "25.5000"
   ]
  },
  "ljubimec": {
   "z": {},
   "l": [
    "41.8333",
    "26.0833"
   ]
  },
  "sipka": {
   "z": {},
   "l": [
    "42.7167",
    "25.3333"
   ]
  },
  "akcha kayryak": {
   "z": {},
   "l": [
    "41.7667",
    "25.4333"
   ]
  },
  "shekhler": {
   "z": {},
   "l": [
    "41.4333",
    "25.3833"
   ]
  },
  "gurkovo": {
   "z": {},
   "l": [
    "42.6667",
    "25.7333"
   ]
  },
  "harmanly": {
   "z": {},
   "l": [
    "41.9333",
    "25.9000"
   ]
  },
  "biser": {
   "z": {},
   "l": [
    "41.8667",
    "25.9833"
   ]
  },
  "ivajlovgrad": {
   "z": {},
   "l": [
    "41.5333",
    "26.1333"
   ]
  },
  "sheinovo": {
   "z": {},
   "l": [
    "42.6833",
    "25.3167"
   ]
  },
  "madjarovo": {
   "z": {},
   "l": [
    "41.6333",
    "25.8667"
   ]
  },
  "dalboki": {
   "z": {
    "6060": [
     "42.4833",
     "25.7667"
    ]
   },
   "l": [
    "42.4833",
    "25.7667"
   ]
  },
  "martino": {
   "z": {},
   "l": [
    "41.7167",
    "25.2667"
   ]
  },
  "bogomilovo": {
   "z": {},
   "l": [
    "42.3833",
    "25.5500"
   ]
  },
  "tulovo": {
   "z": {},
   "l": [
    "42.5833",
    "25.5500"
   ]
  },
  "krun": {
   "z": {},
   "l": [
    "42.6667",
    "25.3833"
   ]
  },
  "gorski izvor": {
   "z": {},
   "l": [
    "41.3500",
    "25.1667"
   ]
  },
  "gruevo": {
   "z": {},
   "l": [
    "41.5667",
    "25.4167"
   ]
  },
  "osetenovo": {
   "z": {
    "6153": [
     "42.6000",
     "25.0333"
    ]
   },
   "l": [
    "42.6000",
    "25.0333"
   ]
  },
  "mishevsko": {
   "z": {},
   "l": [
    "41.5167",
    "25.2500"
   ]
  },
  "elhovo": {
   "z": {
    "8700": [
     "42.5833",
     "25.7500"
    ]
   },
   "l": [
    "42.5833",
    "25.7500"
   ]
  },
  "kasnakovo": {
   "z": {},
   "l": [
    "42.0167",
    "25.5000"
   ]
  },
  "kran": {
   "z": {
    "6140": [
     "41.3333",
     "25.4833"
    ]
   },
   "l": [
    "41.3333",
    "25.4833"
   ]
  },
  "bagra": {
   "z": {},
   "l": [
    "41.7000",
    "25.3167"
   ]
  },
  "varbovo": {
   "z": {},
   "l": [
    "41.7667",
    "25.8667"
   ]
  },
  "ploska mogila": {
   "z": {},
   "l": [
    "42.4333",
    "25.8167"
   ]
  },
  "sofilari": {
   "z": {},
   "l": [
    "42.6667",
    "25.1833"
   ]
  },
  "aydomush": {
   "z": {},
   "l": [
    "41.8000",
    "25.4500"
   ]
  },
  "golema detelina": {
   "z": {},
   "l": [
    "42.2167",
    "26.0333"
   ]
  },
  "gledachevo": {
   "z": {},
   "l": [
    "42.2667",
    "26.0167"
   ]
  },
  "pandakliy": {
   "z": {},
   "l": [
    "42.4000",
    "25.5000"
   ]
  },
  "car asparuh": {
   "z": {},
   "l": [
    "42.4500",
    "25.8500"
   ]
  },
  "lewa reka": {
   "z": {},
   "l": [
    "42.7333",
    "25.6833"
   ]
  },
  "bosduganowo": {
   "z": {},
   "l": [
    "42.3333",
    "25.7667"
   ]
  },
  "gorno gyusovo": {
   "z": {},
   "l": [
    "42.6667",
    "25.5000"
   ]
  },
  "gurbetita": {
   "z": {},
   "l": [
    "42.1667",
    "25.6000"
   ]
  },
  "asukurovo": {
   "z": {},
   "l": [
    "42.2000",
    "25.1167"
   ]
  },
  "cherna gora": {
   "z": {},
   "l": [
    "42.2167",
    "25.2333"
   ]
  },
  "idirlie": {
   "z": {},
   "l": [
    "42.0500",
    "25.5000"
   ]
  },
  "cherni rid": {
   "z": {},
   "l": [
    "41.5167",
    "25.9833"
   ]
  },
  "chakalarovo": {
   "z": {},
   "l": [
    "41.2833",
    "25.3000"
   ]
  },
  "khadzhiolari": {
   "z": {},
   "l": [
    "42.4167",
    "25.2833"
   ]
  },
  "duralii": {
   "z": {},
   "l": [
    "41.9167",
    "25.7167"
   ]
  },
  "kurtolen": {
   "z": {},
   "l": [
    "41.7000",
    "26.0167"
   ]
  },
  "byulyudzhak": {
   "z": {},
   "l": [
    "42.1667",
    "25.7667"
   ]
  },
  "filevo": {
   "z": {},
   "l": [
    "42.0500",
    "25.3500"
   ]
  },
  "khamurzus": {
   "z": {},
   "l": [
    "42.5333",
    "25.5000"
   ]
  },
  "obruchishte": {
   "z": {},
   "l": [
    "42.1333",
    "25.9500"
   ]
  },
  "zhultika": {
   "z": {},
   "l": [
    "41.5167",
    "25.1833"
   ]
  },
  "kara bunar": {
   "z": {},
   "l": [
    "42.3500",
    "25.8333"
   ]
  },
  "stambolovo": {
   "z": {},
   "l": [
    "41.7667",
    "25.6500"
   ]
  },
  "miladinovo": {
   "z": {},
   "l": [
    "41.7000",
    "25.6167"
   ]
  },
  "malko kadievo": {
   "z": {},
   "l": [
    "42.3667",
    "25.7000"
   ]
  },
  "dolno sachrane": {
   "z": {},
   "l": [
    "42.6333",
    "25.2333"
   ]
  },
  "sorgunlii": {
   "z": {},
   "l": [
    "41.7667",
    "25.8667"
   ]
  },
  "kazanka": {
   "z": {},
   "l": [
    "42.4667",
    "25.4167"
   ]
  },
  "matsa": {
   "z": {},
   "l": [
    "42.2167",
    "26.1667"
   ]
  },
  "dolno-sahrane": {
   "z": {},
   "l": [
    "42.6333",
    "25.2333"
   ]
  },
  "strelets": {
   "z": {},
   "l": [
    "42.2833",
    "25.7667"
   ]
  },
  "slatoustowo": {
   "z": {},
   "l": [
    "41.7167",
    "25.8000"
   ]
  },
  "jarebiza": {
   "z": {},
   "l": [
    "41.6167",
    "25.2667"
   ]
  },
  "ovoshtnik": {
   "z": {
    "6138": [
     "41.5500",
     "25.1667"
    ]
   },
   "l": [
    "41.5500",
    "25.1667"
   ]
  },
  "sar yurt": {
   "z": {},
   "l": [
    "41.8000",
    "25.6333"
   ]
  },
  "voynik makhle": {
   "z": {},
   "l": [
    "42.3000",
    "25.1667"
   ]
  },
  "orizovo": {
   "z": {},
   "l": [
    "42.2000",
    "25.1667"
   ]
  },
  "golemo selo": {
   "z": {},
   "l": [
    "42.6500",
    "25.0833"
   ]
  },
  "gluhar": {
   "z": {},
   "l": [
    "41.6000",
    "25.4000"
   ]
  },
  "partizanin": {
   "z": {},
   "l": [
    "42.2500",
    "25.2500"
   ]
  },
  "kadur meschit": {
   "z": {},
   "l": [
    "41.6667",
    "25.3333"
   ]
  },
  "malko": {
   "z": {},
   "l": [
    "41.3500",
    "25.2833"
   ]
  },
  "ivaylovgrad": {
   "z": {},
   "l": [
    "41.5333",
    "26.1333"
   ]
  },
  "kyumyurdzhii": {
   "z": {},
   "l": [
    "41.9000",
    "25.4500"
   ]
  },
  "pshenichevo": {
   "z": {},
   "l": [
    "42.3667",
    "25.8667"
   ]
  },
  "pamukchi": {
   "z": {},
   "l": [
    "42.3167",
    "25.6500"
   ]
  },
  "dervent": {
   "z": {},
   "l": [
    "42.5000",
    "25.6167"
   ]
  },
  "orozovo": {
   "z": {},
   "l": [
    "42.5667",
    "25.4167"
   ]
  },
  "zmeiovo": {
   "z": {},
   "l": [
    "42.5000",
    "25.6167"
   ]
  },
  "lovech": {
   "z": {},
   "l": [
    "42.2500",
    "25.6167"
   ]
  },
  "mineralni bani": {
   "z": {},
   "l": [
    "41.9167",
    "25.3500"
   ]
  },
  "elchovo": {
   "z": {},
   "l": [
    "42.5833",
    "25.7500"
   ]
  },
  "dzebil-oglar": {
   "z": {},
   "l": [
    "41.6167",
    "25.3833"
   ]
  },
  "aleksandrovo": {
   "z": {},
   "l": [
    "41.9833",
    "25.7333"
   ]
  },
  "baba makhle": {
   "z": {},
   "l": [
    "42.1000",
    "25.7333"
   ]
  },
  "byal izvor": {
   "z": {},
   "l": [
    "41.5500",
    "25.0833"
   ]
  },
  "merichleri": {
   "z": {},
   "l": [
    "42.1333",
    "25.5000"
   ]
  },
  "lyubimetz": {
   "z": {},
   "l": [
    "41.8333",
    "26.0833"
   ]
  },
  "glavan": {
   "z": {},
   "l": [
    "42.0667",
    "26.1000"
   ]
  },
  "shipka": {
   "z": {},
   "l": [
    "42.7167",
    "25.3333"
   ]
  },
  "lyubimets": {
   "z": {},
   "l": [
    "41.8333",
    "26.0833"
   ]
  },
  "chiflik makhle": {
   "z": {},
   "l": [
    "42.1667",
    "25.4167"
   ]
  },
  "pirinchlii": {
   "z": {},
   "l": [
    "42.0500",
    "25.7167"
   ]
  },
  "kushlata": {
   "z": {},
   "l": [
    "42.5833",
    "25.6833"
   ]
  },
  "batkanlii": {
   "z": {},
   "l": [
    "42.2167",
    "25.9000"
   ]
  },
  "maslinovo": {
   "z": {},
   "l": [
    "41.7667",
    "25.5333"
   ]
  },
  "kozlevo": {
   "z": {},
   "l": [
    "41.4167",
    "25.2333"
   ]
  },
  "granit": {
   "z": {},
   "l": [
    "42.2500",
    "25.1500"
   ]
  },
  "aladaalii": {
   "z": {},
   "l": [
    "42.1000",
    "25.7833"
   ]
  },
  "ivailovgrad": {
   "z": {
    "6570": [
     "41.5333",
     "26.1333"
    ]
   },
   "l": [
    "41.5333",
    "26.1333"
   ]
  },
  "levka": {
   "z": {},
   "l": [
    "41.8667",
    "26.2667"
   ]
  },
  "druzhintsi": {
   "z": {},
   "l": [
    "41.3333",
    "25.3333"
   ]
  },
  "koprinka": {
   "z": {},
   "l": [
    "42.6333",
    "25.3333"
   ]
  },
  "enina": {
   "z": {},
   "l": [
    "41.9333",
    "26.2333"
   ]
  },
  "buzovgrad": {
   "z": {},
   "l": [
    "42.5667",
    "25.3667"
   ]
  },
  "nova mahala": {
   "z": {},
   "l": [
    "41.8167",
    "25.8833"
   ]
  },
  "podkova": {
   "z": {},
   "l": [
    "41.4000",
    "25.4000"
   ]
  },
  "benkovski": {
   "z": {},
   "l": [
    "41.3833",
    "25.2667"
   ]
  },
  "gabarevo": {
   "z": {},
   "l": [
    "42.6167",
    "25.1667"
   ]
  },
  "zemlen": {
   "z": {},
   "l": [
    "42.3000",
    "25.7833"
   ]
  },
  "yabalkovo": {
   "z": {},
   "l": [
    "42.0667",
    "25.4500"
   ]
  },
  "vulchi dol": {
   "z": {},
   "l": [
    "41.3500",
    "25.3167"
   ]
  },
  "kharmanli": {
   "z": {},
   "l": [
    "41.9333",
    "25.9000"
   ]
  },
  "brusino": {
   "z": {},
   "l": [
    "41.5167",
    "25.9333"
   ]
  },
  "sestrinsko": {
   "z": {},
   "l": [
    "41.7167",
    "25.6333"
   ]
  },
  "dabovo": {
   "z": {},
   "l": [
    "42.6000",
    "25.6500"
   ]
  },
  "rumanya": {
   "z": {},
   "l": [
    "42.5000",
    "25.8667"
   ]
  },
  "kirilovo": {
   "z": {},
   "l": [
    "41.8667",
    "26.1333"
   ]
  },
  "svetlina": {
   "z": {},
   "l": [
    "42.0000",
    "25.3833"
   ]
  },
  "madzharovo": {
   "z": {},
   "l": [
    "41.6333",
    "25.8667"
   ]
  },
  "rakitnitsa": {
   "z": {},
   "l": [
    "42.3333",
    "25.5167"
   ]
  },
  "shumnatitsa": {
   "z": {},
   "l": [
    "41.3000",
    "25.3667"
   ]
  },
  "starozagorski bani": {
   "z": {},
   "l": [
    "42.4500",
    "25.5000"
   ]
  },
  "gorski senovets": {
   "z": {},
   "l": [
    "43.2833",
    "25.9000"
   ]
  },
  "sredno gradishte": {
   "z": {},
   "l": [
    "42.3000",
    "25.3000"
   ]
  },
  "krepost": {
   "z": {},
   "l": [
    "42.0167",
    "25.6000"
   ]
  }
 },
 "l": [
  "41.9403",
  "25.5694"
 ]
}